{"generatedAt":"2026-07-19T20:29:59.195486+00:00","channels":{"24hourfreemovies":false,"00sreplay":true,"70scinema":true,"80srewind":true,"ae":true,"50centaction":true,"aabctv":true,"abc4charlestonsc":true,"90sthrowback":true,"abc2baltimoremd":true,"abc5":true,"abc2portlandor":true,"3abndaretodreamnetwork":true,"3abnlatino":true,"3abnproclaimnetwork":true,"3abnfrench":true,"3abnenglish":true,"3abnkidsnetwork":true,"3abnpraisehimmusicnetwork":true,"30aridiculoustv":true,"abc5bostonma":true,"30amusic":true,"30aloomeredtv":true,"30atelevisionchannel":true,"30ainvestmentpitch":true,"30awelovecars":true,"90skidstv2":true,"30alionelnationtv":true,"abc10sandiegoca":true,"30agolfkingdom":true,"30ageorgiahollywoodreviewtv":true,"30adarcizzleoffshore":true,"30athebeachshow":true,"30asidewalks":true,"30aluxelifediscovered":true,"30atvclassicmovies":true,"90skids":true,"abc9manchesternh":true,"abc6indianapolisin":false,"abc4seattlewa":true,"abc27tallahasseefl":true,"abc9orlandofl":true,"abc7albuquerquenm":true,"abc9tucsonaz":true,"abc23bakersfieldca":true,"abc12milwaukeewi":true,"abc13lasvegasnv":true,"abc7denverco":true,"abc25newscentraltexas":true,"abc5stpaulmn":true,"abc6austintx":true,"abc13ashevillenc":true,"abc15myrtlebeachfl":true,"abc6columbusoh":true,"abcnewslive1":true,"abcnewslive7":true,"abcnewslive6":true,"abcnewslive8":true,"abcnewslive9":true,"abcnewslive4":true,"abcnewslive10":true,"abc15phoenixaz":true,"abc22daytonoh":true,"abc7washingtondc":true,"abnafghanistan":true,"abnbiblemovies":true,"abnchina":true,"abnafrica":true,"accdn":true,"abcnewslive3":true,"access4pac":true,"abcnewslive2":true,"abcnewslive5":true,"abntvindia":true,"abnurdu":true,"48hours":true,"accessmediaproductionsmontereychannel":true,"afrolandtv":true,"accesssacramentochannel17":true,"accessmediaproductionschannel":true,"accessmediaproductionscommunitychannel":true,"accessmediaproductionsmarinatv":true,"accessmediaproductionspeninsulachannel":true,"accesstuolumne":true,"actv":true,"afvenespaolnot247":false,"accnetwork":true,"accuweathernow":true,"akaku53":true,"akaku54":true,"akaku55":true,"alhorreyatv":true,"abcwway3":true,"akctv":true,"alfadytvnot247":true,"accessnashua":true,"akctvpuppies247":true,"akctvmeetthebreeds":true,"alkarmatvaustralia":true,"accessvisionchannel16":true,"aftv":true,"accessvisionchannel17":true,"acetv":true,"almahditv":true,"abc10duluthmn":true,"accesshumboldt":true,"allblkgems":true,"alkarmatvtalmazanot247":true,"alkarmatvpraisenot247":true,"alkarmatvfamilynot247":true,"alkarmatvmiddleeastnot247":true,"amc":true,"abc":false,"adrenalinapuratv":true,"albdreamstv":true,"alabamaweathernetwork":true,"allweddingswetvgeoblocked":true,"amgatvnot247":true,"abcwest":true,"almagdtvmiddleeastnot247":true,"alwaysfunnyvideos":true,"allrealitywetv":true,"altitudesports":false,"aghapykids":true,"americasvoice":true,"americasvoicenews":true,"alhurrairaq":true,"amcenespaolgeoblocked":true,"artntvnot247":true,"amcabsolutereality":true,"alientovisionnot247":true,"amceast":false,"amgtv":true,"americasfunniesthomevideos":true,"americastestkitchengeoblocked":true,"arkansaspbsgeoblocked":true,"assyriasatnot247":true,"amazingfactstv":true,"angermanagementchannel":true,"asiancrush":true,"ameritradenot247":true,"abcmiamifl":true,"animexhidivegeoblocked":true,"animationgeoblocked":true,"arydigitalusanot247":false,"atlantachannel":true,"athomewithfamilyhandyman":true,"alkarmatvyouthenglishnot247":true,"antiquesroadshowpbs":true,"alkarmatvnorthamericacanadanot247":true,"antiquesroadshowuk":true,"axstv":true,"artflixmovieclassics":true,"atlas":true,"auroratv":true,"aspire":true,"arewethereyet":true,"almagdtvnorthamerica":true,"autentichistory":false,"aweinternational":true,"autentictravel":false,"barktv":true,"backstage":true,"bbcamerica":true,"atl26":true,"asianculturetv":true,"awe":true,"babytvlatinamerica":true,"bbcfood":true,"b4umoviesusa":false,"atxn2":true,"bbcdoctorwhoclassic":true,"bandamaxusa":true,"americasnexttopmodel":true,"aweplus":true,"bbchomegarden":true,"atxn3":true,"beachtvfloridaalabama":true,"beachtvmyrtlebeachthegrandstrand":true,"babyfirst":true,"baywatch":true,"babysharktv":true,"beinsportsusa":true,"avangtv":true,"beinsportsxtraenespanol":true,"atxn1":true,"beachtvpanamacity":true,"berkscommunitytv":true,"beinsportsxtra":true,"beachtvkeywestfloridakeys":true,"amutv":true,"babytvus":true,"bbcearth":true,"bbckids":false,"bektvnews":true,"beverlyhillstelevision10":true,"bektvsportswest":true,"beverlyhillstelevision35":true,"americanhorrors":true,"bigcivicchannel":true,"betcinema":true,"betcomedymovies":true,"bigcommunitychannel":true,"bigtennetwork":true,"acapulcoshore":true,"betterlifetv":true,"betterlifenaturechannel":true,"blacknewschannel":true,"binge":true,"billiardtvgeoblocked":true,"biztv":true,"blazelive":true,"blackfamilysitcoms":true,"bloombergtv":true,"betthrowbacks":true,"bloombergoriginals":true,"bigbrother":true,"bluestv":true,"beyondthegates":true,"bloomfieldaccessgovernmenttv":true,"betterhealthtv":true,"bloomfieldaccesstvchannel5":true,"blackinkcrew":true,"bounce":true,"boltoncommunityvoicechanneleducation":true,"bet":false,"betjams":true,"bether":false,"betherwest":true,"boltoncommunityvoicechannelgovernment":true,"betgospel":true,"boltoncommunityvoicechannelpublic":true,"betsoul":true,"betwest":true,"bloombergtvusliveevent":true,"britboxmysteries":true,"bravowest":true,"bloombergtvuspoliticsliveevent":true,"bonapptit":true,"bouncexl":true,"buzzr":true,"butv10not247":true,"bpxtvradio":true,"byutv":true,"bxinform":true,"bxarts":true,"businessrockstars":true,"buenaparktelevision":true,"brevardcountygovernmentaccesstv":true,"bxinspire":true,"burbankchannel":true,"bravo":true,"brattv":true,"californiamusicchannel":true,"bmchdtv":true,"canaldelafe":true,"bonanza":true,"canelatv":true,"campspoopy":true,"calabasaschannel":true,"catchycomedy":true,"carlsbadcitytvchannel":true,"catholictv":true,"cbs2saltlakecityut":true,"camerasmile":true,"cbs8desmoinesia":true,"cbs4elpasotx":true,"cbs3omahane":true,"cafetradetv":true,"cbnespanol":true,"cbs6richmondva":true,"cbnnewschannel":true,"cbs12cincinnatioh":true,"bxomni":true,"cbs12westpalmbeachfl":true,"cbnfamily":true,"cantv21":true,"cantv36":false,"cantv27":true,"cantv19":true,"cbs42austintx":true,"cbsnews247":true,"cbs3kalamazoomi":true,"cbsnewsbaltimore":true,"cbsnewsmiami":true,"cbs9oklahomacityoknot247":true,"cbsnewsnewyork":true,"cbsnewsminnesota":true,"cbssportsgolazonetwork":false,"cbs21harrisburgpa":true,"cbsnewschicago":true,"cbsnewsboston":true,"cbsnewssacramento":true,"cbsnewscolorado":true,"cbs22southbendin":true,"bxculture":true,"cbs":true,"cbsnewsphiladelphia":true,"cbsnewspittsburgh":true,"channel11":true,"channel18gac":true,"cbsnewsbayarea":true,"celebritynamegamegeoblocked":true,"cbssportshqgeoblocked":true,"bellatormma":true,"cbsnewsdetroit":true,"ccx1":true,"cerritostv3":true,"cfmtvchannel98":true,"charge":true,"cbsnewslosangeles":true,"channel10":true,"cfncatholicfaithnetwork":true,"chinohillscitytvchannel341":true,"bestofdrphil":true,"cineenespaol":true,"channelone":true,"christianyouthchannel":true,"charlottecountycctv":true,"betclassics":true,"cinepremiere":true,"cinemexicano":true,"cheddarnews":true,"cineterror":true,"chefrocshownot247":true,"cinevault80s":false,"chefchampionnot247":true,"cinevaultwesterns":false,"barrescue":true,"cinesony":true,"cineromantico":false,"citytvsandiego":true,"choppertown":true,"cbswest":true,"cityofmonroegovernmentchannel":true,"citytvcapitalcityconnectionnot247":true,"classicmoviewesterns":true,"classictvcomedy":true,"cheersfrasier":true,"classicmovieschannel":true,"clarity4kgeoblocked":true,"circle":true,"cinepride":true,"classictvfamilies":true,"classica":true,"classiccinemanot247":true,"cityofoakland":true,"cmt":true,"cloudflaretv":true,"cmtequalplay":true,"cineamor":true,"cmcusacountrymusicchannel":true,"access19":false,"comedycentral":true,"battlestargalactica":true,"cineadrenalina":true,"coldcasefiles":true,"coasttvnbcnot247":false,"comedydynamics":false,"cookingpanda":true,"celebrityscenetv":true,"concordtv":true,"comet":true,"cornerstonetv":true,"comerciotv":true,"cbsenespaol":true,"courttv":true,"creatvclassroomschannel28":true,"cops":true,"creatvbayvoicetvchannel27":true,"creatvtheoutletchannel30":true,"creatvcommunitychannel15":true,"champaigngovernmenttelevision":true,"create":true,"comedycentralenespaol":true,"coralgablestelevision":false,"comedycentralplutotv":true,"costamesasmunicipalaccesschannelcmtv3":true,"costv":true,"csi":true,"crimeinvestigation":true,"cruztv":true,"concertchannel":true,"csattvnot247":true,"crime360":true,"comedycentralanimation":true,"cupertinocitychannel":false,"cleotv":true,"csimiamienespaol":true,"ctn":true,"cnbc":true,"cvtvchannel194":true,"cvtvchannel192":true,"curiositynow":true,"ctntvconneticutnot247":true,"ctnlivestream2not247":true,"ctncourtfeednot247":true,"dabl":true,"cypresspublicaccesschannel36":true,"cineaventura":true,"darkmattertv":true,"dccouncilchannel":true,"dcgovcouncilhearingroom120":true,"dateline247":false,"contracostacollegetvgeoblocked":true,"dangertv":true,"delmartv":false,"crmenesimperfectos":true,"derrytv17":true,"depeliculaus":true,"denver8tv":true,"degrassi":true,"csienespaol":true,"dcgovdkn":true,"csimiami":true,"dealornodeal":true,"derrytv23":true,"detroitchannel22":true,"colliertelevisionctv":false,"degatvnot247":false,"detroitchannel21":true,"detroitchannel10":true,"disneyjunior":true,"disneyxd":true,"districtofcolumbianetwork":true,"designatedsurvivorgeoblocked":true,"betplutotv":true,"betvisionaries":true,"dccmakingtheteam":true,"documentary":false,"divaadria":false,"cozitv":true,"beverlyhillbillies":true,"beverlyhills90210":true,"daystartv":true,"dogelcazarrecompensas":true,"daystarespaol":true,"dovechannel":true,"cinecomedia":true,"detroitchannel68":true,"drphilsmerittv":true,"e":true,"drgenescott":true,"draftkingsnetwork":true,"dungeontv":true,"ebonytvbylionsgate":true,"duckhuntingtv":true,"drybarcomedy":true,"dogthebountyhunter":true,"donttellthebride":true,"entertainmenttonight":true,"elsembradornuevaevangelizacionesne":true,"ekeepingup":true,"disneyxdwest":true,"elbesharagtvnot247":true,"crunchyroll":true,"dynasty":true,"espndeportes":true,"aewest":false,"electricnowgeoblocked":true,"elrey":false,"etvteluguusa":true,"escambiacountytvectv":false,"espnu":true,"elreinoinfantil":true,"entrepreneurtv":true,"ebscinema":true,"estrellasdeaccin":true,"espnews":false,"extrematv":true,"ebsmusika":true,"fairfieldgovernmentaccesschannel26geoblocked":true,"carchase":true,"estrellagames":true,"fandueltv":true,"estrellanews":true,"fcpublicmedia":true,"docurama":false,"ewtnspanishgeoblocked":true,"estrellatv":true,"fernandinabeachcitymeetingnot247":true,"fashionfinds":true,"f1channelgeoblocked":true,"fifaunitedstates":false,"failarmyinternational":true,"filmriseanime":true,"ewtngeoblocked":true,"fite247":false,"flicksoffury":true,"fgtv":true,"classictvdrama":true,"forensicfiles":true,"fearfactor":true,"fontanacommunitytelevisiongeoblocked":true,"filmrisewesterns":true,"feelgooddrama":true,"fortcollinscabletv":true,"foreverkids":true,"filmriseclassictv":false,"fox2sanfranciscoca":true,"fnxgeoblocked":true,"fnx":true,"fideletv":false,"forensicfilesgeoblocked":true,"fox13seattlewa":true,"fox26visaliaca":true,"fox23capegirardeaumonot247":true,"fox45baltimoremd":true,"fox11greenbaywi":true,"foxsoul":false,"fox25oklahomacityok":true,"filamtvnetwork":true,"foxbusinessnetwork":true,"familyties":true,"foxnewsradio":true,"farscape":true,"fortpiercelivestream":true,"fresnocmac1publicchannel":true,"freeform":true,"freebietvnot247":false,"foxnewschannel":false,"fresnocmac2educationchannel":true,"fresnocmac3governmentchannel":true,"foxdeportes":false,"freespeechtv":true,"flowerstvusa":false,"fubosportsnetwork":true,"foxweathergeoblocked":true,"datingdisasters":true,"foxsports1":true,"fuse":true,"fx":true,"fxx":true,"frightflix":true,"ftfsports":true,"funroads":true,"disneychannel":true,"disneychannelwest":true,"galxytv":true,"gainesvillecommunity12tv":true,"disneyjuniorwest":true,"didgahtv":true,"ganjehozourtv":true,"gameshowcentral":true,"gebtv":true,"funnyaf":true,"bluebloods":true,"gemshoppingnetwork":true,"fox":true,"gillettepublicaccesstelevisionchannel189":true,"gagsnetwork":true,"gillettepublicaccesstelevisionchannel190":true,"gilroycmaptvchannel18":true,"gilroycmaptvchannel19":true,"gilroycmaptvchannel20":true,"foxwest":true,"gillettepublicaccesstelevisionchannel192":true,"glendale11az":true,"gbnglobalbuddhistnetwork":true,"girlfriends":true,"garfieldandfriends":true,"glendaletvgeoblocked":true,"godslearningchannel":true,"gilroycmaptvchannel17":true,"dogtv":true,"goldencommunitytelevision":true,"goodlife45not247":true,"gousatv":true,"golfchannel":false,"globalfashionchannel":true,"gospeltruthtv":true,"gotravelergeoblocked":true,"gordonramsay":true,"greatamericanfamily":true,"guangdongtvamerica":true,"gravitasmovies":true,"classictvcrimedrama":true,"fox25bostongeoblocked":true,"csiny":true,"grjngowesternmovies":true,"gritxtra":true,"hallmarkfamily":true,"gospelbroadcastingnetwork":true,"hallmarkchannel":true,"hallmarkmoviesmore":false,"fanduelracing":false,"harpalgeo":false,"hallmarkmystery":true,"go2travel":false,"greensborotv":true,"haddamkillingworthhighschooltvgeoblocked":true,"happykids":true,"fetv":true,"highvisionnot247":true,"hasbrolegendsgeoblocked":true,"golazonetwork":true,"hctvgovernmentchannel":true,"hctveducationalaccesschannel":true,"heartland":true,"csinyenespaol":true,"hiyah":true,"hctvpublicaccesschannel":true,"gunsmoke":true,"freeformwest":true,"history":true,"happydays":true,"gmtv":true,"haunttv":true,"hmongstartvnot247":true,"hmongtvnetwork":true,"gunaztv":true,"homeful":true,"hisglorytv":true,"historyhit":true,"hollywire":true,"hillsboroughcountytvhtv":true,"hsn":true,"hsn2":true,"hmipromznews":true,"hogansheroes":true,"gameshownetwork":true,"fyi":true,"hsnwest":true,"humormill":false,"htv2houstontelevision":true,"htv1houstontelevision":true,"hope4lifetv":false,"inthekitchen":true,"hotbench":true,"hopechannelinternational":true,"hopechannelnorthamerica":true,"ifc":true,"hungry":true,"impactnetwork":true,"globalchristiannetworkamerica":true,"i24newsenglishusa":false,"instantsaga":true,"insp":true,"impossiblequizshow":true,"infast":true,"hopechannelinteramericaenglish":true,"hopechannelinteramerica":true,"huntingtonbeachtvchannel3":true,"inwild":true,"itiswrittentv":true,"greatamericanfaithliving":true,"ionplus":true,"greatentertainmenttelevision":true,"grit":true,"itssupernaturalnetwork":false,"homemadenation":true,"jacksonvilleonslowgovernmenttelevision":true,"infowarsnetwork":true,"investiga":true,"globalworldtv":true,"jewishlifetelevision":true,"judgenosey":true,"iongeoblocked":true,"icarlytv":true,"justicecentraltv":true,"jbs":true,"journytv":true,"iranefardatv":false,"inkmaster":true,"kcontentbycjenm":true,"harvestusa":true,"kbevspectrumchannel6beverlyhills":false,"kbribrightonchannel8":false,"kaloopytv":true,"justforlaughsgags":true,"kcatpublicmediatv":true,"ironchef":true,"kdfwdt1":true,"kerncountytelevision":true,"kcksld253":true,"kcmnld6":true,"kajoutvnot247":true,"kftrdt1geoblocked":true,"kmexdt1geoblocked":true,"jewelrytelevision":true,"kidsflixnot247":true,"ketchuptv":true,"kmspdt1":true,"kpvmacecountryradio":true,"kirodt1":true,"kidsmovieclub":true,"kpvmmovies":true,"kpvmaweplus":true,"kartoonchannel":true,"jewelrytv2":true,"kntvdt1":false,"kpvmoanplus":true,"kpvmnewsmax2":true,"kokidt1":true,"kpvmrealamericasvoice":true,"kitv4islandnews":true,"kdvr311":true,"krgvdt2geoblocked":true,"kpvmprimetv25":true,"kpvmstorytelevision":true,"krcatvestrellalosangeles":true,"krisdt1":true,"krivdt1":true,"kscevidacristiana":true,"kshb41":true,"kuvndt1":true,"kvvbtv33victorvalleynot247":true,"kttvdt1":true,"ksazdt1":true,"ktbcdt1":true,"kviedt2":true,"lacrossetv":true,"kqeddt2":true,"kztvdt1":true,"kxasdt1":false,"laff":true,"lawndalecitytv":false,"ktoo360tv3":false,"lavozdejesushd":true,"kqslchannel8":true,"lakewoodcitytv":true,"latvgeoblocked":true,"legokidstv":true,"lacityview35":false,"kadntv151":true,"laquebuenaatlanta":true,"indimusictv":false,"leesburglakefronttv":true,"lakewoodchannel8":false,"klfytv101":true,"leominstertvgovernment":true,"lasvegastonightwithdaledavidson":true,"jerseyshore":true,"latinochanneltv":true,"leominstertveducational":true,"lifechristianbroadcastingnetwork":true,"lbcinternational":true,"lifeendtimestv":true,"ilovelucy":true,"lifetime":true,"lifetimerealwomen":true,"lifetimemovies":true,"leominstertvpublicnot247":true,"lgtv":true,"lextv":true,"lhcaztv":true,"lightinglivesblessingnationstvlatino":true,"lightinglivesblessingnationshisword":true,"lightinglivesblessingnationstvchinese":true,"lightinglivesblessingnationssmartlifestyletv":true,"lifevisiontvnot247":true,"katc31":true,"lightinglivesblessingnationstvromanian":true,"lightinglivesblessingnationstvsouthasia":true,"lightinglivesblessingnationstvkorean":true,"lightinglivesblessingnationshislight":true,"livemusic":true,"localish":true,"lindelltv":true,"littleton8tv":false,"littlestarsuniverse":true,"logostvnot247":false,"livenowfromfoxgeoblocked":true,"littleguyanatv":true,"lolnetwork":false,"longbeachtelevision":true,"lightinglivesblessingnationstvarabic":true,"livexlive":true,"lompoctaptvchannel23":true,"lompoctaptvchannel24":true,"lompoctaptvchannel25":true,"lawcrime":true,"lonestar":true,"losangeleslocaltelevisionchannel36":true,"lovepets":true,"lovehiphop":true,"logoplutotv":true,"logostvenglishnot247":true,"lptv":true,"lovetheplanet":true,"lovenatureenespanolgeoblocked":true,"luckydog":true,"lovelandtv":true,"losnuevosdetectives":true,"madeinhollywood":true,"magellantvnow":true,"magnificentmoviesnetwork":true,"loveworldusa":true,"logo":true,"logostvkidsnot247":true,"logostvestudionot247":false,"mariavisionusa":true,"maverickblackcinema":true,"manateeschoolstelevisionmstv":true,"logostvsaludnot247":false,"maddogandmerrillnot247":true,"luchalibreaaa":false,"mediasetitaliausa":true,"martincountymctv":true,"mcn6artschannelnot247":true,"mcn6not247":true,"metv":true,"mcn6musicchannelnot247":true,"majestadtelevisinnot247":true,"mbcmasrusa":true,"miamibeachtv":true,"midnightpulp":true,"matlock":true,"mbc1usageoblocked":true,"mbc3usageoblocked":true,"mbcamerica":true,"mbcdramausa":true,"minutoparaganar":true,"millbraecommunitytelevision":false,"midsomermurders":true,"metaleitortv":true,"misteriosmedicos":true,"missiontvnot247":true,"misteriossinresolver":true,"missionimpossible":true,"mlbstrikezone":true,"mlbchannelgeoblocked":true,"ministeriolavozdeunremanentetv":true,"mohabattv":true,"mobilecountypublicschoolstvnetwork":true,"mmatv":true,"metvtoons":true,"monroecommunitymediaeducationchannel":true,"monroecommunitymediapublicaccesschannel":true,"msadrenalina":true,"monroecountytelevisionmctv":true,"montgomerychannel":true,"moviesphere":true,"movies":false,"moretvdrama":true,"moorparkgovernmentchannel":false,"msnow":true,"mrvtvchannel45":true,"mrbeananimated":true,"mrvtvchannel44":true,"moretruecrime":true,"kmctdt1":false,"livingfaithtv":false,"moretvsitcoms":true,"msg2":false,"mtv":true,"mtv2":true,"msg":true,"motortrendfasttv":true,"mtvlive":true,"mst3k":true,"mtvbiggestpop":true,"mtvspankinnew":true,"mysterysciencetheater3000":true,"mtctv":true,"mytvsanantoniotxnot247":true,"mytimemovienetwork":true,"naruto":true,"nashuaetvchannel22nashuanh":true,"mtvenespaol":true,"nashbridgeschannelgeoblocked":true,"nattv":true,"natickgovernmentchannel":true,"natickeducationchannel":true,"nashuagtvchannel16nashuanh":true,"foxsports2":false,"nationalgeographic":true,"nationalgeographichdeast":true,"natickpublicaccesschannel":true,"fyiwest":false,"nationalgeographicwild":true,"nationalgeographicwildhdeast":true,"galavision":false,"galavisionwestgeoblocked":false,"nbc3sacramentoca":true,"nbc3lasvegasnv":true,"galvestoncountytvnot247":false,"nbc4milwaukeewi":true,"nbc4sanantoniotx":true,"nbc4albuquerquenm":true,"nbc6santabarbaraca":true,"nbatvgeoblocked":true,"nbc6johnstownpa":true,"nbc8lancasterpa":true,"nbc5chicagolivenews":false,"nbc11baltimoremd":true,"nbc8salinasca":true,"nbc9steubenvilleoh":true,"mtvflowlatino":true,"nbc12winstonsalemnc":true,"nbclxhome":true,"nbc13albanyny":true,"nbcnewsnow":false,"nbc10rochesterny":true,"nbcsportsnow":false,"nbc8limaohnot247":false,"nbc26greenbaywi":true,"nbcuniversowest":true,"nbcwestnot247":true,"nbclx":true,"nbcsn":true,"nbccomedyvault":true,"nbcuniverso":true,"ncmeducationalkidschannel":true,"nesn":false,"ncmgovernmentpolitics":true,"newcanaantelevision79":true,"ncmmainchannel":true,"nbcwest":true,"nbc":true,"newportbeachtelevision":false,"nbc10providencema":true,"news12connecticutgeoblocked":true,"news12longislandgeoblocked":true,"historywest":false,"news12hudsonvalleygeoblocked":false,"mtvclassic":true,"news12newyorkgeoblocked":true,"mtvu":true,"news12brooklyngeoblocked":true,"news12newyork":true,"mtvplutotv":true,"newsmaxtv":true,"newsnation":true,"imantv":false,"newsmax2":true,"newsmaxspanish":true,"news12westchestergeoblocked":true,"newsnetnot247":true,"nationalgeographicwest":true,"nhratv":true,"ibtvusa":false,"nflnetwork":true,"nhlnetwork":true,"nickjr":true,"newsy":true,"jushindi":false,"jusone":false,"juspunjabi":false,"nflchannelgeoblocked":true,"nickelodeon":true,"nickelodeonplutotv":true,"ninjakidz":true,"nbcnewsnowhd":true,"nostthenostalgianetwork":false,"nbcsportschicago":true,"nickelodeonenespaol":true,"notvneworleanstv":true,"nosey":true,"norcastweather":true,"northmiamibeachtv":true,"ntdtvenglish":true,"nickjrplutotv":true,"nyxt":true,"newkmovies":true,"olelocommunitymediachannel49":true,"ntdtvwest":true,"olelocommunitymediachannel53":true,"olelocommunitymediachannel54":true,"oanplus":true,"olelocommunitymediachannel55":true,"oneamericanewsnetwork":true,"ontariopublicaccesschannel":true,"ntdtv":true,"oceansidecommunitytelevisioneducationandgovernmentchannel19":true,"oceansidecommunitytelevisioncommunitychannel18":true,"newkpop":true,"orangegovernmentaccesstv":true,"outside":false,"outdoorchannel":true,"outdoorchannelhd":true,"omideiran":true,"ocntv":true,"outdooramerica":true,"outersphere":true,"ontv4ugeoblocked":true,"ovation":true,"oxygen":true,"overcomerstv":true,"overtime":true,"nrbtv":true,"pacificcoasttvmwsdchannel26":true,"paramountmoviechannel":true,"pacificcoasttvhmbcoastsidechannel27":true,"paramountnetwork":true,"paramountpicks":true,"onepiece":true,"pac12insider":true,"palmbeachestv":true,"lifetimemovieswest":false,"payameafghantvnot247":true,"lifetimewest":false,"pasiones":true,"nicktoons":true,"pbctapeshtv":true,"palmbeachcountytvchannel20":true,"payamearameshtv":true,"nicktoonswest":true,"pbsket2":true,"pbsantiquesroadtrip":true,"pbsketworld":true,"pbsketky":true,"pbsketlouisvilleky":true,"onceninasyninos":false,"pbshonoluluhinot247":true,"pascotv":false,"payamjavantvnot247":true,"parstv":true,"pbslincolnnegeoblocked":true,"pbskidseasterncentral":true,"pbsretrogeoblocked":false,"pacificislandnetwork":true,"pbrridepass":true,"pbsmptbaltimoremd":true,"pbsnewjerseynjnot247":true,"pbsnature":true,"pbsnationaleastgeoblocked":true,"peopleareawesome":true,"peppapig":true,"pbskidsalaska":true,"pbskidspacific":true,"pbstravel":true,"pbskidshawaii":true,"pbskidsmountain":true,"phxtv":true,"pinolecommunitytelevisionchannel26":true,"plutotvaction":true,"pbssedaliabritishcolumbiamogeoblocked":true,"plutotvanimemovies":true,"phlgovtv":true,"phillycam":true,"plutotvcars":true,"pgatour":true,"novelisima":false,"placidnot247":true,"pixltv":true,"pinolecommunitytelevisionchannel28":true,"plutotvdrama":true,"plutotvcrimemovies":true,"payvandtv":true,"plutotvanime":true,"plutotvfantastic":true,"perrymason":true,"pbskids":true,"pbskids247":false,"plutotvicons":true,"plutotvfranchisefavorites":true,"plutotvgameshows":true,"plutotvlives":true,"plutotvhistory":true,"plutotvromance":true,"plutotvhometowndrama":true,"mgmmarquee":false,"mgmwest":false,"plutotvspotlight":true,"plutotvnovelas":true,"midpenmediacenterartsissuesandlifestyleschannel30":false,"plutotvstaffpicks":true,"plutotvterror":true,"plutotvthrillers":true,"midpenmediacenterdiversityandculturechannel75":false,"midpenmediacentergovernmentetcchannel26":false,"midpenmediacentergovernmentetcchannel29":false,"plutotvscience":true,"midpenmediacenteryoutheducationandsportschannel28":false,"plutotvwesterns":true,"plutotvcrimedrama":true,"pocketwatchgameon":true,"pokergo":false,"popstartv":false,"portstluciepsltv":true,"poptv":true,"positivtv":true,"plutotvpride":true,"poconotelevisionnetwork":true,"portlandia":true,"plutotvparanormal":true,"pursuitchannel":true,"qvc":true,"pursuitup":true,"qvc3":true,"ptltelevisionnetwork":false,"plutotvhorror":true,"pompanobeachwebstreaming":true,"poudreschooldistricttv":true,"raiworldpremium":true,"powernation":true,"plutotvtruecrime":true,"mlbnetwork":false,"pottadivinetvusa":true,"pomonainternetstreamingchannel":true,"radioytelevisinmart":true,"rainbowruby":true,"radiotlkajounot247":false,"ranchocucamongarctv3":true,"realwild":true,"reelzfamousinfamous":false,"rallytv":true,"radiotelepuissance":true,"radiotlwisdomnot247":false,"radiotelesentinel":true,"reuters":true,"plutotvcomedy":true,"revandroll":true,"redbulltvus":false,"revrynewsnot247":false,"retrocrush":true,"realamericasvoice":false,"revolt":true,"redseatthefirst":true,"rifftrax":true,"rfdtv":true,"rightnowtv":false,"riflecommunitytvrctv":true,"roar":true,"plutotvcultfilms":true,"retrotv":false,"revnaction":false,"revry":true,"revryqueer":true,"plutotvcompetition":true,"rthtv1":true,"plutotvbackcountry":true,"rtenespanol":true,"redapple21not247":true,"swat":false,"rtvius":true,"radiomensajetv":true,"qvc2":true,"salemnewschannel":true,"rvtvgrantspass":true,"sanskarusa":false,"rvtvcivic":true,"rvtvprime":true,"rvtvvoices":true,"rockyhillgovernmentaccesschannel16":false,"runtimeespanol":true,"ridiculousness":true,"samsungwildlifegeoblocked":true,"rvtvgeoblocked":true,"ryanandfriends":true,"santamonicacitytv20not247":true,"revryher":false,"sccurrents":true,"sanctuary":true,"scrippsnews":true,"santamariacommunitytelevisioneducationchannel":true,"santamariacommunitytelevisiongovernmentchannel":true,"revrylatinx":true,"plutotvmilitary":true,"plutotvscifi":true,"santamariacommunitytelevisionpublicaccesschannel":true,"plutotvadventure":true,"secnetwork":true,"schwabnetwork":true,"scientologynetworkkscndt1":false,"screendreams":true,"sfgovtv2sanfranciscothecitychannel":true,"sfgovtvsanfranciscothegovernmentchannel":true,"semillitastv":true,"shoplc":true,"scientologynetwork":false,"scientologynetworkwfttdt1":false,"plutotvtrendingnow":true,"showtime":false,"shouttv":true,"shemaroobollywood":true,"showtimefamilyzone":true,"sgtv":true,"soreal":false,"snlvault":false,"skwad":true,"smithsonianchannel":true,"pokmon":true,"smithsonianchannelselects":true,"sfcommonschannel76":true,"runtime":true,"sfcommonschannel29":true,"sketchyaf":true,"slopestv":true,"shalomtvnot247":true,"sonycanalnovelas":false,"slocountychannel21":true,"sonictv":true,"shabakeh7":true,"sportsmanchannel":true,"sportsnetnewyork":true,"soundviewcommunitymediaeducation":true,"scvtv":true,"stpetetv":true,"sbntv":true,"sonykalhindi":true,"senttvglobalnetworkatlanta":true,"spikeoutdoors":true,"starttv":true,"starz":true,"stadium":true,"stluciepublicschools":true,"starzcinema":true,"news12newjerseygeoblocked":false,"spirittvnot247":true,"starzcomedy":true,"storytelevision":true,"starzkidsfamily":true,"stocktongovtv":false,"sportsgrid":true,"storiesbyamc":true,"sumtvenglish":true,"sumtvlatino":true,"sundancetv":true,"startrekthenextgeneration":true,"stingraygreatestholidayhits":false,"survivor":true,"plutotvreaction":true,"supersimplesongs":true,"swervecombat":true,"news12bronxgeoblocked":false,"scaresbyshudder":true,"spikeplutotv":true,"startrekvoyager":true,"talkinliveclassicstv":true,"speedvision":false,"sitcomlegends":true,"rtrplanetausageoblocked":true,"tbninspire":true,"news12conneticutgeoblocked":false,"tbn":true,"stryktv":true,"storagewarsbyae":true,"tastemadetravel":true,"tastemade":true,"syfy":true,"ted":true,"tampabaycommunnitynetworktbcn":true,"teennick":true,"taiwanplustv":false,"telepam":true,"starinternational":true,"telemix":true,"superchannelorlando":true,"telemundocorpuschristi":true,"rawhide":true,"telehitestadosunidos":true,"telehitmusicaestadosunidos":true,"tempoafrictv":true,"telemundoaldia":false,"teleboston":true,"thebobrosschannel":false,"tbnarmenia":true,"tapesh2":true,"thearchive":true,"tct":true,"terramaterwildenglish":true,"thechallenge":true,"theasylum":true,"tempechannel11":true,"tennischannel2":true,"thehilltvgeoblocked":false,"thefilmdetective":true,"tevevidanetworknot247":true,"thecarolburnettshow":true,"tennischannel":true,"swamijitvamericannot247":true,"teenmom":true,"thefirsttv":true,"thegrahamnortonshow":true,"thejohnnycarsonshow":true,"thelegochannel":true,"thecountrynetwork":true,"thechatshowchannel":true,"theconnersgeoblocked":true,"thedesignnetwork":true,"temeculatv":true,"thejamieoliverchannel":true,"supernaturaldrama":true,"thewalktv":false,"thepriceisrightthebarkererageoblocked":true,"theohiochannel":false,"thepriceisright":true,"theyoungturksgeoblocked":true,"thenest":true,"theaddamsfamily":true,"theamazingrace":true,"theloveboat":true,"thenownetworknot247":true,"thepetcollectivegeoblocked":true,"threescompany":true,"thisoldhouse":true,"thewordnetwork":true,"tbnpacific":true,"timelesstv":true,"toongogglesjunior":true,"todayallday":true,"thewalkingdeaduniverse":true,"tomandjerry":true,"thegoodwife":true,"tlnmediasanfrancisco":true,"torranceciticable":false,"toongoggles":true,"topstoriesbynewsy":true,"tmzgeoblocked":true,"thorntongovernmentaccesschannel17":true,"thenewdetectives":true,"thedovetv":true,"tlnmediachicago":true,"toonamiaftermatheast":true,"truecrimenow":true,"tintv":true,"thetwilightzone":true,"thewalkingdeadenespaol":true,"tstv":true,"thecowboychannel":true,"tutv":true,"tosh0":true,"totallyturtles":true,"startrek":true,"traverseareacommunitymediacommunitytvchannel189geoblocked":true,"tvland":true,"tribecachannelgeoblocked":true,"thewildwildwest":true,"truecrimenetworkgeoblocked":true,"tvdajanot247":false,"tvlanddrama":true,"tvone":true,"tinyhousenation":true,"transformerstv":true,"telemundotelenovelasclsicas":true,"truehistory":true,"tvhispanicnot247":true,"turismohd":true,"tv4":true,"startrekdeepspacenine":true,"tvpanounot247":true,"tvquisqueya":true,"tvsciphernetwork":true,"tvsclassicmovies":true,"tvscomedynetwork":true,"tvsclassicsports":true,"tvsfamilychannel":true,"tvsflashbacknetwork":true,"tvshitops":true,"tvsdriveinmovie":true,"tvshollywoodhistory":true,"tvsmainstreetnot247":true,"tvsmusicnetwork":true,"tvlandsitcoms":true,"tvsnostalgiamovies":true,"tvsboxing":true,"tvsnostalgia":true,"tvsquizshownetwork":true,"tvspinballnetwork":true,"tveinternacionalamericageoblocked":true,"tveinternacionalamericahdgeoblocked":true,"tvspetparadenetwork":true,"tvssportsbureau":true,"tvssportsnot247":true,"tvstalknetwork":true,"tvstavern":true,"tvstelevisionnetwork":true,"tvstravelnetworknot247":true,"tvsagovernmentchannel":true,"tvsapublicchannel":true,"tvsturbo":true,"unidentified":true,"uctvuniversityofcalifornianot247":true,"nickelodeonwest":false,"unimascentral":true,"tvswesternmovie":true,"tvsvintagenetwork":true,"unbeaten":false,"tvswomensports":true,"univision":true,"unimasmountain":true,"tvsselectnetwork":true,"tvsconsumerdirect":true,"uptv":true,"usanetwork":true,"usanetworkwest":true,"tvstallyho":true,"thejudgejudychannel":true,"unsolvedmysteries":true,"vevo2k":true,"tycsportsusa":true,"usatoday":true,"vevo70s":true,"vevo80s":true,"venevisininternacional":true,"theandygriffithshow":true,"vevolatino":true,"vevocountry":true,"vevopop":true,"vevo90s":true,"vevoretrorock":true,"vbstvnot247":true,"vevohiphop":true,"valleyshorecommunitytelevision":true,"vevorb":true,"vh1":true,"vh1west":true,"vevotrueschoolhiphop":true,"visionlatinanetwork":true,"tvsbowlingnetwork":true,"vicetv":true,"villageofhastingsonhudsonny":true,"universalcrime":true,"universalcomedy":true,"vegaslifetv":true,"w14dkd141tvdelmarva":true,"wanteddeadoralive":true,"w14dkd142newsnet":true,"w14dkd145allsportstelevisionnetwork":false,"voatvafrica":true,"vidamejortv":true,"voapersian":true,"vh1queensofreality":true,"vtnvictorytelevisionnetwork":true,"univisionwest":false,"therifleman":true,"watctheloop":true,"velayattv":true,"watchitscream":true,"watchitkid":true,"wcetvdigitalchannel318":true,"watctv57":true,"wbtscd1":false,"wcaudt1":false,"wbrzweatherchannelbatonrougela":true,"wbtvnews":true,"universalcinema":false,"wetv":true,"weathernation":true,"weatherspy":true,"waypointtv":true,"wedqdt4":true,"westerntv":true,"wflddt1":true,"wfutdt1geoblocked":true,"wggsdt1":false,"watcthepointnetwork":true,"wftxnewsfortmyersfl":true,"wgaldt3geoblocked":true,"vallenatointernacionalnot247":false,"wggsdt2":true,"wcot13":true,"wfxtdt2":true,"wgndt1":true,"vsin":true,"toughjobs":true,"wgtvdt3":true,"westerns4u":true,"wcbi":true,"wcca194worcesterma":true,"weedsnursejackie":true,"westhollywoodwehotv":true,"whiplashcinema":true,"whiteplainscommunitymedia":true,"whiodt1":true,"willowsports":true,"wdeftvnewschattanoogatn":true,"whbqdt1":true,"wired2fishgeoblocked":true,"whiplash":true,"whpsdetroit":true,"wltvdt1geoblocked":true,"whiplashii":true,"witidt1":true,"windowtv":true,"wjbkdt1":true,"whittiercitytv":true,"winewatcheswhiskey":true,"wildnout":true,"wmptdt2":true,"wlmb":true,"witn22not247":false,"wipeoutxtra":true,"wjaxdt1":true,"wnbcdt1":false,"wlngradionot247":true,"wnywdt1":true,"wcbstv21":true,"womenssportsnetwork":true,"worldfishingnetwork":true,"worldpokertour":false,"wpstv":true,"worldchannel":true,"willow":true,"wptvnewswestpalmbeachfl":true,"wdaftv42":true,"wsocnowgeoblocked":true,"wolcottgovernmentaltv":false,"wslfld351":true,"wrcdt1":false,"wpxidt1":true,"wtvjdt1":true,"wutangcollection":false,"wipeout":true,"wxtvdt1":true,"wtvtdt1":true,"wsocdt1":true,"wvvhcd181":true,"wsbdt1":true,"wbbj":true,"wtxfdt1":true,"wttgdt1":true,"worldharvesttv":true,"wtnhdt1":true,"wvitdt1":false,"wmgttvnews":true,"xitejustchill":true,"xiterockxmetal":true,"xitereggaevibes":true,"youdotgov":true,"wsbsdt1":true,"xfctv":true,"yesnetwork":true,"wvculpconcorduniversityradiothecure977":true,"winthropcommunityaccesstvnot247":false,"xitenuevolatino":false,"xite90sthrowback":false,"xitesiemprelatino":false,"younghollywoodgeoblocked":true,"wtvqabc36news":true,"wwontvch48":true,"yugiohenespanol":true,"yahoofinance":true,"ytatv":true,"yugioh":true,"yumaazch72":true,"zarintv":true,"wjxtnews4jax":true,"xplore":true,"yumaazch73":true,"xiteclassiccountrygeoblocked":true,"yomtv":true,"wxxvtvnews":true,"wwordt1":false,"yuma77":true,"zoomtvkurdish":true,"international":true,"wmbcdt1":false,"syfywest":false,"telemundowest":false,"telemundo":false,"tudn":false,"tvsfilmnoirnetwork":false,"unimas":false,"unimaswestgeoblocked":false,"univisiontlnovelas":false,"vallejocommunityaccesstelevision":false}}