{"generatedAt":"2026-07-22T16:59:43.237634+00:00","channels":{"24hourfreemovies":false,"3abnproclaimnetwork":true,"3abnpraisehimmusicnetwork":true,"3abnlatino":true,"3abnkidsnetwork":true,"3abnenglish":true,"3abnfrench":true,"3abndaretodreamnetwork":true,"90sthrowback":true,"50centaction":true,"90skids":true,"abc5":true,"ae":true,"abc5stpaulmn":true,"abc4seattlewa":true,"abc2portlandor":true,"abc6austintx":true,"30ainvestmentpitch":true,"abc5bostonma":true,"30aridiculoustv":true,"30atelevisionchannel":true,"30agolfkingdom":true,"30atvclassicmovies":true,"30awelovecars":true,"30alionelnationtv":true,"30ageorgiahollywoodreviewtv":true,"abc6indianapolisin":false,"30adarcizzleoffshore":true,"30athebeachshow":true,"30aluxelifediscovered":true,"30amusic":true,"30asidewalks":true,"30aloomeredtv":true,"abc7albuquerquenm":true,"abc":false,"aabctv":true,"abcnewslive1":true,"abcnewslive2":true,"abc4charlestonsc":true,"abc7washingtondc":true,"abcnewslive4":true,"abcnewslive3":true,"abc9tucsonaz":true,"abc12milwaukeewi":true,"abc9orlandofl":true,"abcnewslive7":true,"abc9manchesternh":true,"abc10duluthmn":true,"abcnewslive6":true,"abcnewslive8":true,"abcnewslive5":true,"abcnewslive9":true,"abc7denverco":true,"abc25newscentraltexas":true,"80srewind":true,"abc2baltimoremd":true,"accnetwork":true,"abcnewslive10":true,"90skidstv2":true,"abc6columbusoh":true,"abnchina":true,"abnurdu":true,"abntvindia":true,"abnafghanistan":true,"abnafrica":true,"abnbiblemovies":true,"abc13ashevillenc":true,"abc22daytonoh":true,"abc13lasvegasnv":true,"accdn":true,"access4pac":true,"abc27tallahasseefl":true,"abc10sandiegoca":true,"abc23bakersfieldca":true,"abc15phoenixaz":true,"accessmediaproductionsmontereychannel":true,"access19":true,"accessmediaproductionsmarinatv":true,"accessmediaproductionschannel":true,"accessmediaproductionspeninsulachannel":true,"accessmediaproductionscommunitychannel":true,"accuweathernetwork":true,"afvenespaolnot247":false,"actv":true,"abcmiamifl":true,"akaku54":true,"akaku53":true,"akaku55":true,"akctv":true,"accuweathernow":true,"abc15myrtlebeachfl":true,"alhorreyatv":true,"accesstuolumne":true,"alfadytvnot247":true,"akctvmeetthebreeds":true,"akctvpuppies247":true,"alhurrairaq":true,"allrealitywetv":true,"acetv":true,"abcwway3":true,"alkarmatvpraisenot247":true,"alkarmatvmiddleeastnot247":true,"alkarmatvtalmazanot247":true,"alkarmatvfamilynot247":true,"altitudesports":false,"albdreamstv":true,"amc":true,"almahditv":true,"acapulcoshore":true,"allweddingswetvgeoblocked":true,"alabamaweathernetwork":true,"aghapykids":true,"accesssacramentochannel17":true,"almagdtvmiddleeastnot247":true,"allblkgems":true,"alkarmatvaustralia":true,"amcabsolutereality":true,"americasvoicenews":true,"alientovisionnot247":true,"americanhorrors":true,"amceast":false,"amazingfactstv":true,"alwaysfunnyvideos":true,"adrenalinapuratv":true,"amgtv":true,"americasvoice":true,"amgatvnot247":true,"antennatv":true,"amcenespaolgeoblocked":true,"alkarmatvnorthamericacanadanot247":true,"alkarmatvyouthenglishnot247":true,"americastestkitchengeoblocked":true,"aspire":true,"antiquesroadshowpbs":true,"ameritradenot247":true,"48hours":true,"accessvisionchannel17":true,"almagdtvnorthamerica":true,"artflixmovieclassics":true,"artntvnot247":true,"americasfunniesthomevideos":true,"aftv":true,"angermanagementchannel":true,"atlantachannel":true,"accessnashua":true,"accessvisionchannel16":true,"antiquesroadshowuk":true,"assyriasatnot247":true,"atl26":true,"arewethereyet":true,"atlas":true,"arkansaspbsgeoblocked":true,"asiancrush":true,"animexhidivegeoblocked":true,"babyfirst":true,"autentictravel":false,"axstv":true,"babytvus":true,"awe":true,"athomewithfamilyhandyman":true,"autentichistory":false,"bbcamerica":true,"babysharktv":true,"barrescue":true,"bbcamericaeasthd":true,"battlestargalactica":true,"backstage":true,"babytvlatinamerica":true,"b4umoviesusa":false,"bbcdoctorwhoclassic":true,"beachtvfloridaalabama":true,"bandamaxusa":true,"beachtvpanamacity":true,"00sreplay":true,"bbcfood":true,"beachtvmyrtlebeachthegrandstrand":true,"atxn2":true,"animationgeoblocked":true,"barktv":true,"atxn1":true,"atxn3":true,"bbchomegarden":true,"bbcearth":true,"arydigitalusanot247":false,"avangtv":true,"beinsportsusa":true,"betgospel":true,"beinsportsxtraenespanol":true,"betherwest":true,"aweplus":true,"bellatormma":true,"baywatch":true,"betjams":true,"beinsportsxtra":true,"beachtvkeywestfloridakeys":true,"betsoul":false,"aweinternational":true,"betwest":true,"betclassics":true,"betcinema":true,"betcomedymovies":true,"asianculturetv":true,"amutv":true,"beverlyhillbillies":true,"betplutotv":true,"betthrowbacks":true,"betvisionaries":true,"berkscommunitytv":true,"70scinema":true,"accesshumboldt":true,"auroratv":true,"betterlifenaturechannel":true,"betterlifetv":true,"blackfamilysitcoms":true,"beverlyhillstelevision35":true,"betterhealthtv":true,"abcwest":true,"biztv":true,"bbckids":false,"bigtennetwork":true,"bigcommunitychannel":true,"bigcivicchannel":true,"bluebloods":true,"bluestv":true,"beverlyhillstelevision10":true,"bloombergtv":true,"billiardtvgeoblocked":true,"blacknewschannel":true,"bounce":true,"boltoncommunityvoicechanneleducation":true,"binge":true,"bloombergoriginals":false,"bet":false,"boltoncommunityvoicechannelpublic":true,"boltoncommunityvoicechannelgovernment":true,"bether":false,"bravowest":true,"bloombergtvuspoliticsliveevent":true,"bloomfieldaccessgovernmenttv":true,"bloomfieldaccesstvchannel5":true,"britboxmysteries":true,"bonapptit":true,"butv10not247":true,"buzzr":true,"bxinform":true,"bpxtvradio":true,"bravo":true,"blackinkcrew":true,"bloombergtvusliveevent":true,"bmchdtv":true,"bektvsportswest":true,"bektvnews":true,"buenaparktelevision":true,"bestofdrphil":true,"bouncexl":true,"byutv":true,"brattv":true,"cspan2":true,"cspan":true,"businessrockstars":true,"californiamusicchannel":true,"campspoopy":true,"cantv27":false,"cantv19":true,"cantv21":true,"cantv36":false,"beverlyhills90210":true,"beyondthegates":true,"catchycomedy":true,"bxarts":true,"bxculture":true,"bxinspire":true,"bxomni":true,"bigbrother":true,"canaldelafe":true,"canelatv":true,"catholictv":true,"camerasmile":true,"cbnfamily":true,"cbnnewschannel":true,"cbs8desmoinesia":true,"carlsbadcitytvchannel":true,"brevardcountygovernmentaccesstv":true,"cbnespanol":true,"cbs6richmondva":true,"burbankchannel":true,"cbsnews247":true,"cbs22southbendin":true,"cbs21harrisburgpa":true,"cbs42austintx":true,"cafetradetv":true,"cbs12cincinnatioh":true,"cbsnewscolorado":true,"cbsnewssacramento":true,"cbs3omahane":true,"cbs3kalamazoomi":true,"cbsnewsbaltimore":true,"cbssportsnetworkusa":true,"bonanza":true,"cbsnewsboston":true,"cbsnewsbayarea":true,"cbsnewschicago":true,"cbs":true,"cbsnewsminnesota":true,"americasnexttopmodel":true,"cbs2saltlakecityut":true,"ccx1":true,"calabasaschannel":true,"cbsnewsphiladelphia":true,"cbsnewspittsburgh":true,"cbs4elpasotx":true,"cbsnewsdetroit":true,"cheddarbusiness":true,"cbsnewslosangeles":true,"cbsnewsnewyork":true,"cbsnewsmiami":true,"cbssportshqgeoblocked":true,"cbssportsgolazonetwork":false,"chinohillscitytvchannel341":true,"champaigngovernmenttelevision":true,"celebritynamegamegeoblocked":true,"celebrityscenetv":true,"cineadrenalina":true,"channel11":true,"cinepremiere":true,"chefrocshownot247":true,"chefchampionnot247":true,"charge":true,"choppertown":true,"cbswest":true,"cbs12westpalmbeachfl":true,"christianyouthchannel":true,"cbs9oklahomacityoknot247":true,"cineromantico":false,"cfncatholicfaithnetwork":true,"cinevault80s":false,"cinemexicano":true,"cinevaultwesterns":false,"channelone":true,"channel18gac":true,"cinesony":true,"classicmovieschannel":true,"carchase":true,"classictvcrimedrama":true,"cleotv":true,"cfmtvchannel98":true,"cheddarnews":true,"cinepride":true,"classicmoviewesterns":true,"cbsenespaol":true,"charlottecountycctv":true,"channel10":true,"cerritostv3":true,"clarity4kgeoblocked":true,"citytvsandiego":true,"citytvcapitalcityconnectionnot247":true,"classiccinemanot247":true,"cloudflaretv":true,"classictvcomedy":true,"cmt":true,"circle":true,"classica":true,"cnbc":true,"comedytv":true,"coasttvnbcnot247":false,"cityofmonroegovernmentchannel":true,"cmtequalplay":true,"coldcasefiles":true,"comedycentralplutotv":true,"comedycentralanimation":true,"comedycentral":true,"concertchannel":true,"comet":true,"comedycentralenespaol":true,"cookingpanda":true,"cineamor":true,"cozitv":true,"cornerstonetv":true,"colliertelevisionctv":false,"cmcusacountrymusicchannel":true,"concordtv":true,"cityofoakland":true,"cops":true,"comedydynamics":false,"cheersfrasier":true,"contracostacollegetvgeoblocked":true,"create":true,"crimeinvestigation":true,"costv":true,"csienespaol":true,"comerciotv":true,"csattvnot247":true,"courttv":true,"cupertinocitychannel":false,"creatvclassroomschannel28":true,"creatvbayvoicetvchannel27":true,"creatvtheoutletchannel30":true,"creatvcommunitychannel15":true,"dabl":true,"curiositynow":true,"cineaventura":true,"cruztv":true,"ctntvconneticutnot247":true,"cw":true,"ctnlivestream2not247":true,"ctncourtfeednot247":true,"ctn":true,"coralgablestelevision":false,"costamesasmunicipalaccesschannelcmtv3":true,"classictvdrama":true,"dcgovdkn":true,"dcgovcouncilhearingroom120":true,"cvtvchannel192":true,"dateline247":false,"cypresspublicaccesschannel36":true,"cvtvchannel194":true,"darkmattertv":true,"dccouncilchannel":true,"afrolandtv":true,"degatvnot247":false,"depeliculaus":true,"dangertv":true,"designatedsurvivorgeoblocked":true,"classictvfamilies":true,"denver8tv":true,"disneychannel":true,"discoveryturbo":true,"detroitchannel68":true,"disneychannelwest":true,"dealornodeal":true,"disneyxd":true,"disneyjuniorwest":true,"daystarespaol":true,"crime360":true,"disneyjunior":true,"crmenesimperfectos":true,"districtofcolumbianetwork":true,"crunchyroll":true,"csimiamienespaol":true,"csiny":true,"detroitchannel10":true,"degrassi":true,"dogtv":true,"detroitchannel22":true,"detroitchannel21":true,"divaadria":false,"csinyenespaol":true,"daystartv":true,"donttellthebride":true,"drybarcomedy":true,"didgahtv":true,"dovechannel":true,"drphilsmerittv":true,"draftkingsnetwork":true,"e":true,"blazelive":true,"documentary":false,"dogthebountyhunter":true,"dungeontv":true,"datingdisasters":true,"ekeepingup":true,"drgenescott":true,"ebonytvbylionsgate":true,"ebscinema":true,"espndeportes":true,"duckhuntingtv":true,"derrytv23":true,"ewest":true,"elrey":false,"ebsmusika":true,"elsembradornuevaevangelizacionesne":true,"etvteluguusa":true,"derrytv17":true,"espnu":true,"entertainmenttonight":true,"entrepreneurtv":true,"fanduelracing":false,"electricnowgeoblocked":true,"ewtngeoblocked":true,"estrellagames":true,"cineterror":true,"ewtnspanishgeoblocked":true,"fandueltv":true,"espnews":false,"escambiacountytvectv":false,"fernandinabeachcitymeetingnot247":true,"f1channelgeoblocked":true,"elbesharagtvnot247":true,"estrellanews":true,"failarmyinternational":true,"fetv":true,"estrellatv":true,"fashionfinds":true,"extrematv":true,"filmriseclassictv":false,"fideletv":false,"fifaunitedstates":false,"fairfieldgovernmentaccesschannel26geoblocked":true,"disneyxdwest":true,"flix":true,"fite247":false,"fgtv":true,"flowerstvusa":false,"foreverkids":true,"forensicfilesgeoblocked":true,"filmrisewesterns":true,"fnxgeoblocked":true,"fortpiercelivestream":true,"fearfactor":true,"filmriseanime":true,"dogelcazarrecompensas":true,"docurama":false,"fox25oklahomacityok":true,"csimiami":true,"fox13seattlewa":true,"foxbusinessnetwork":true,"fox2sanfranciscoca":true,"dynasty":true,"fox23capegirardeaumonot247":true,"fox11greenbaywi":true,"fox45baltimoremd":true,"fox26visaliaca":true,"foxnewsradio":true,"foxnewsinternational":true,"fcpublicmedia":true,"elreinoinfantil":true,"fnx":true,"foxsoul":false,"freeformwest":true,"foxsports2":false,"foxsoccerplus":true,"foxdeportes":false,"foxnewschannel":false,"ftfsports":true,"familyties":true,"foxsports1":true,"fontanacommunitytelevisiongeoblocked":true,"fortcollinscabletv":true,"freebietvnot247":false,"estrellasdeaccin":true,"freeform":true,"fubosportsnetwork":true,"feelgooddrama":true,"filamtvnetwork":true,"fyi":true,"fresnocmac1publicchannel":true,"frightflix":true,"foxweathergeoblocked":true,"fuse":true,"freespeechtv":true,"gameshownetwork":true,"fx":true,"farscape":true,"cineenespaol":true,"fxx":true,"fresnocmac3governmentchannel":true,"gameshowcentral":true,"fox":true,"foxwest":true,"gainesvillecommunity12tv":true,"fox25bostongeoblocked":true,"fxm":true,"forensicfiles":true,"gillettepublicaccesstelevisionchannel189":true,"gillettepublicaccesstelevisionchannel192":true,"gillettepublicaccesstelevisionchannel190":true,"glendale11az":true,"galxytv":true,"girlfriends":true,"gebtv":true,"fresnocmac2educationchannel":true,"gilroycmaptvchannel17":true,"gbnglobalbuddhistnetwork":true,"ganjehozourtv":true,"gagsnetwork":true,"godslearningchannel":true,"funroads":true,"flicksoffury":true,"gemshoppingnetwork":true,"gousatv":true,"goodlife45not247":true,"golfchannel":false,"greatamericanfaithliving":true,"greatamericanfamily":true,"gospeltruthtv":true,"globalworldtv":true,"greatentertainmenttelevision":true,"globalfashionchannel":true,"gravitasmovies":true,"gmtv":true,"grit":true,"gotravelergeoblocked":true,"gordonramsay":true,"csi":true,"go2travel":false,"hallmarkfamily":true,"funnyaf":true,"greensborotv":true,"fxmoviechannel":true,"grjngowesternmovies":true,"hallmarkmystery":true,"gilroycmaptvchannel19":true,"hallmarkmoviesmore":false,"hallmarkchannel":true,"gilroycmaptvchannel18":true,"gilroycmaptvchannel20":true,"gospelbroadcastingnetwork":true,"happykids":true,"gritxtra":true,"glendaletvgeoblocked":true,"garfieldandfriends":true,"hctvpublicaccesschannel":true,"hasbrolegendsgeoblocked":true,"guangdongtvamerica":true,"haddamkillingworthhighschooltvgeoblocked":true,"heartland":true,"history":true,"goldencommunitytelevision":true,"historyhit":true,"hogansheroes":true,"haunttv":true,"highvisionnot247":true,"cinecomedia":true,"hmipromznews":true,"hisglorytv":true,"hctveducationalaccesschannel":true,"gunaztv":true,"hctvgovernmentchannel":true,"hollywire":true,"homeful":true,"harpalgeo":false,"hmongstartvnot247":true,"hmongtvnetwork":true,"hiyah":true,"hsn":true,"hsn2":true,"htv2houstontelevision":true,"htv1houstontelevision":true,"hope4lifetv":false,"hsnwest":true,"icarlytv":true,"ifc":true,"hillsboroughcountytvhtv":true,"happydays":true,"humormill":false,"inthekitchen":true,"impactnetwork":true,"i24newsenglishusa":false,"impossiblequizshow":true,"hopechannelinternational":true,"hungry":true,"globalchristiannetworkamerica":true,"hopechannelnorthamerica":true,"insp":true,"infowarsnetwork":true,"gunsmoke":true,"hopechannelinteramerica":true,"hopechannelinteramericaenglish":true,"itssupernaturalnetwork":false,"harvestusa":true,"infast":true,"huntingtonbeachtvchannel3":true,"itiswrittentv":true,"homemadenation":true,"inwild":true,"jbs":true,"jacksonvilleonslowgovernmenttelevision":true,"ionplus":true,"iongeoblocked":true,"justicecentraltv":true,"jewishlifetelevision":true,"iranefardatv":false,"ilovelucy":true,"kadntv151":true,"judgenosey":true,"kaloopytv":true,"kajoutvnot247":true,"justforlaughsgags":true,"journytv":true,"kcontentbycjenm":true,"inkmaster":true,"kcatpublicmediatv":true,"kcksld253":true,"dccmakingtheteam":true,"jewelrytv2":true,"kbevspectrumchannel6beverlyhills":false,"kbribrightonchannel8":false,"kcmnld6":true,"investiga":true,"ketchuptv":true,"kerncountytelevision":true,"jewelrytelevision":true,"klfytv101":true,"kidsflixnot247":true,"kmexdt1geoblocked":true,"kftrdt1geoblocked":true,"katc31":true,"kpvmaweplus":true,"kpvmacecountryradio":true,"kartoonchannel":true,"kdvr311":true,"ironchef":true,"kpvmmovies":true,"kdfwdt1":true,"kitv4islandnews":true,"kntvdt1":false,"kpvmnewsmax2":true,"kpvmoanplus":true,"kpvmrealamericasvoice":true,"kmctdt1":false,"kpvmstorytelevision":true,"kpvmprimetv25":true,"golazonetwork":true,"krcatvestrellalosangeles":true,"kirodt1":true,"krgvdt2geoblocked":true,"kuvndt1":true,"kscevidacristiana":true,"kmspdt1":true,"kshb41":true,"kxasdt1":false,"kvvbtv33victorvalleynot247":true,"krivdt1":true,"kztvdt1":true,"ksazdt1":true,"kttvdt1":true,"aewest":false,"laff":true,"ktbcdt1":true,"kokidt1":true,"kqslchannel8":true,"kqeddt2":true,"kviedt2":true,"kidsmovieclub":true,"lawcrime":true,"lawndalecitytv":false,"lavozdejesushd":true,"legokidstv":true,"lacrossetv":true,"lakewoodcitytv":true,"leominstertveducational":true,"lacityview35":false,"krisdt1":true,"leominstertvgovernment":true,"latvgeoblocked":true,"ktoo360tv3":false,"lifechristianbroadcastingnetwork":true,"lbcinternational":true,"lifetime":true,"leominstertvpublicnot247":true,"lgtv":true,"lifetimerealwomen":true,"lifeendtimestv":true,"lakewoodchannel8":false,"laquebuenaatlanta":false,"lifetimemovies":true,"leesburglakefronttv":true,"indimusictv":false,"lifevisiontvnot247":true,"lightinglivesblessingnationstvchinese":true,"lightinglivesblessingnationssmartlifestyletv":true,"lightinglivesblessingnationshislight":true,"lasvegastonightwithdaledavidson":true,"lightinglivesblessingnationstvkorean":true,"lightinglivesblessingnationstvarabic":true,"littlestarsuniverse":true,"lightinglivesblessingnationstvromanian":true,"latinochanneltv":true,"lightinglivesblessingnationshisword":true,"lextv":true,"livingfaithtv":false,"instantsaga":true,"lindelltv":true,"logo":true,"lightinglivesblessingnationstvsouthasia":true,"lightinglivesblessingnationstvlatino":true,"lhcaztv":true,"localish":true,"littleguyanatv":true,"lolnetwork":false,"lompoctaptvchannel23":true,"livenowfromfoxgeoblocked":true,"logostvnot247":false,"littleton8tv":false,"longbeachtelevision":true,"lonestar":true,"lompoctaptvchannel24":true,"lovenatureenespanolgeoblocked":true,"hotbench":true,"lompoctaptvchannel25":true,"lovehiphop":true,"luchalibreaaa":false,"lovepets":true,"logostvenglishnot247":true,"luckydog":true,"lovetheplanet":true,"maddogandmerrillnot247":true,"madeinhollywood":true,"lptv":true,"magellantvnow":true,"losangeleslocaltelevisionchannel36":true,"lovelandtv":true,"livexlive":true,"mariavisionusa":true,"marqueesportsnetwork":true,"magnificentmoviesnetwork":true,"loveworldusa":true,"maverickblackcinema":true,"losnuevosdetectives":true,"logostvsaludnot247":false,"logostvkidsnot247":true,"logostvestudionot247":false,"manateeschoolstelevisionmstv":true,"mediasetitaliausa":true,"mcn6musicchannelnot247":true,"mcn6not247":true,"mcn6artschannelnot247":true,"majestadtelevisinnot247":true,"metv":true,"metvtoons":true,"jerseyshore":true,"matlock":true,"mgm":true,"mgmdrivein":true,"miamibeachtv":true,"martincountymctv":true,"metaleitortv":true,"mbc1usageoblocked":true,"midpenmediacentergovernmentetcchannel26":true,"midpenmediacenterartsissuesandlifestyleschannel30":true,"midpenmediacenterdiversityandculturechannel75":true,"midpenmediacentergovernmentetcchannel29":true,"midsomermurders":true,"midnightpulp":true,"mbcamerica":true,"mbcmasrusa":true,"livemusic":true,"mbcdramausa":true,"mbc3usageoblocked":true,"mlbnetwork":true,"mlbchannelgeoblocked":true,"midpenmediacenteryoutheducationandsportschannel28":false,"mlbstrikezone":true,"mohabattv":true,"ministeriolavozdeunremanentetv":true,"monroecountytelevisionmctv":true,"mobilecountypublicschoolstvnetwork":true,"moretruecrime":true,"missiontvnot247":true,"moretvdrama":true,"montgomerychannel":true,"moretvsitcoms":true,"millbraecommunitytelevision":false,"monroecommunitymediapublicaccesschannel":true,"movies":false,"moviesphere":true,"monroecommunitymediaeducationchannel":true,"msnow":true,"mmatv":true,"msg2":true,"mrbeananimated":true,"mrvtvchannel44":true,"msgplus":true,"mtv":true,"msg":true,"mtv2":true,"mtvclassic":true,"missionimpossible":true,"misteriosmedicos":true,"minutoparaganar":true,"mtvlive":true,"mtvu":true,"mtvenespaol":true,"mtvplutotv":true,"misteriossinresolver":true,"mtvflowlatino":true,"mtvbiggestpop":true,"mst3k":true,"moorparkgovernmentchannel":false,"mtvspankinnew":true,"mytvsanantoniotxnot247":true,"nashbridgeschannelgeoblocked":true,"mysterysciencetheater3000":true,"mrvtvchannel45":true,"nationalgeographic":true,"nashuaetvchannel22nashuanh":true,"mtctv":true,"mytimemovienetwork":true,"nationalgeographicwest":true,"nationalgeographichdeast":true,"natickeducationchannel":true,"nashuagtvchannel16nashuanh":true,"nationalgeographicwild":true,"nationalgeographicwildhdeast":true,"naruto":true,"logoplutotv":true,"nattv":true,"nbc5chicagolivenews":false,"nbc3lasvegasnv":true,"nbc4albuquerquenm":true,"nbc3sacramentoca":true,"nbc4sanantoniotx":true,"nbatv":true,"nbc6johnstownpa":true,"muslimnetworktv":false,"nbc9steubenvilleoh":true,"nbc8limaohnot247":true,"nbc":true,"nbc8salinasca":true,"nbc8lancasterpa":true,"nbclxhome":true,"nbc11baltimoremd":true,"nbc4milwaukeewi":true,"nbc12winstonsalemnc":true,"nbcnewsnow":false,"nbc6santabarbaraca":true,"nbc10rochesterny":true,"nbcnewsnowhd":true,"nbc13albanyny":true,"nbcsportschicago":true,"nbc26greenbaywi":true,"nbccomedyvault":true,"nbclx":true,"nbcsn":true,"nbcsportsnow":false,"nbcwestnot247":true,"motortrendfasttv":true,"msadrenalina":true,"nbcuniversowest":true,"natickpublicaccesschannel":true,"ncmmainchannel":true,"nesn":false,"ncmgovernmentpolitics":true,"natickgovernmentchannel":true,"newcanaantelevision79":true,"ncmeducationalkidschannel":true,"news12longislandgeoblocked":true,"news12newjerseygeoblocked":true,"news12hudsonvalleygeoblocked":true,"nbcuniverso":true,"newportbeachtelevision":false,"news12bronxgeoblocked":true,"news12newyorkgeoblocked":true,"newsmaxtv":true,"news12brooklyngeoblocked":true,"news12conneticutgeoblocked":true,"newsnation":true,"nbcwest":true,"newsnetnot247":true,"newsmaxspanish":true,"news12westchestergeoblocked":true,"newsmax2":true,"nickjr":true,"news12newyork":true,"nflnetwork":true,"nickelodeonenespaol":true,"nicktoons":true,"newsy":true,"nickelodeonplutotv":true,"nickjrplutotv":true,"nickelodeon":true,"nicktoonswest":true,"nbc10providencema":true,"nhlnetwork":true,"nosey":true,"nhratv":true,"novelisima":false,"delmartv":false,"nflchannelgeoblocked":true,"notvneworleanstv":true,"ntdtv":true,"ninjakidz":true,"nostthenostalgianetwork":false,"nownewsusa":true,"nownewsspanish":true,"nownewsarabic":true,"nyxt":true,"oanplus":true,"ntdtvenglish":true,"nrbtv":true,"norcastweather":true,"olelocommunitymediachannel49":true,"oneamericanewsnetwork":true,"olelocommunitymediachannel53":true,"northmiamibeachtv":true,"olelocommunitymediachannel54":true,"onceninasyninos":false,"olelocommunitymediachannel55":true,"ntdtvwest":true,"orangegovernmentaccesstv":true,"outdoorchannelhd":true,"ontariopublicaccesschannel":true,"ovation":true,"omideiran":true,"oceansidecommunitytelevisioncommunitychannel18":true,"outdooramerica":true,"outside":false,"oceansidecommunitytelevisioneducationandgovernmentchannel19":true,"oxygen":true,"outersphere":true,"outdoorchannel":true,"pacificcoasttvhmbcoastsidechannel27":true,"pac12insider":true,"paramountmoviechannel":true,"ocntv":true,"overtime":true,"ontv4ugeoblocked":true,"paramountnetwork":true,"pacificcoasttvmwsdchannel26":true,"palmbeachestv":true,"payamearameshtv":true,"overcomerstv":true,"payamjavantvnot247":true,"onepiece":true,"pascotv":false,"payameafghantvnot247":true,"payvandtv":true,"pbshonoluluhinot247":true,"parstv":true,"pbsketlouisvilleky":true,"pbskids":true,"pbsket2":true,"pbskids247":true,"pbsketky":true,"pasiones":true,"pbrridepass":true,"pbsantiquesroadtrip":true,"pbctapeshtv":false,"pacificislandnetwork":true,"pbsketworld":true,"pbskidseasterncentral":true,"pbsretrogeoblocked":false,"pbsmptbaltimoremd":true,"palmbeachcountytvchannel20":true,"pbsnewjerseynjnot247":true,"pbsnature":true,"pbslincolnnegeoblocked":true,"galvestoncountytvnot247":false,"pbsnationaleastgeoblocked":true,"peopleareawesome":true,"fyiwest":false,"galavision":false,"galavisionwestgeoblocked":false,"pbskidsalaska":true,"pbskidshawaii":true,"pbskidspacific":true,"pbskidsmountain":true,"pbstravel":true,"plutotvanimemovies":true,"plutotvanime":true,"plutotvadventure":true,"phlgovtv":true,"phillycam":true,"pixltv":true,"plutotvbackcountry":true,"pbssedaliabritishcolumbiamogeoblocked":true,"plutotvcompetition":true,"plutotvcomedy":true,"phxtv":true,"plutotvcars":true,"plutotvcrimedrama":true,"plutotvfranchisefavorites":true,"plutotvcultfilms":true,"plutotvgameshows":true,"pgatour":true,"plutotvhometowndrama":true,"newkpop":true,"plutotvhorror":true,"newkmovies":true,"plutotvmilitary":true,"placidnot247":true,"pinolecommunitytelevisionchannel26":true,"plutotvromance":true,"plutotvscifi":true,"pinolecommunitytelevisionchannel28":true,"plutotvreaction":true,"peppapig":true,"plutotvpride":true,"plutotvspotlight":true,"plutotvthrillers":true,"plutotvterror":true,"plutotvwesterns":true,"pocketwatchgameon":true,"plutotvscience":true,"poconotelevisionnetwork":true,"pokergo":false,"historywest":false,"poptv":true,"popstartv":false,"plutotvdrama":true,"positivtv":true,"plutotvhistory":true,"plutotvtrendingnow":true,"plutotvparanormal":true,"portlandia":true,"pursuitchannel":true,"pompanobeachwebstreaming":true,"powernation":true,"plutotvtruecrime":true,"qvc":true,"pottadivinetvusa":true,"qvc2":true,"imantv":false,"portstluciepsltv":true,"qvc3":true,"pomonainternetstreamingchannel":true,"radiotelesentinel":true,"radiotlwisdomnot247":false,"raiworldpremium":true,"radiotlkajounot247":false,"poudreschooldistricttv":true,"radiotelepuissance":true,"pursuitup":true,"pokmon":true,"rawhide":true,"ibtvusa":false,"ptltelevisionnetwork":false,"reelzfamousinfamous":false,"jushindi":false,"jusone":false,"juspunjabi":false,"realwild":true,"rainbowruby":true,"retrocrush":true,"realamericasvoice":false,"redbulltvus":false,"ranchocucamongarctv3":true,"plutotvnovelas":true,"radioytelevisinmart":true,"rfdtv":true,"revrynewsnot247":false,"redseatthefirst":true,"rallytv":true,"revandroll":true,"ridiculousness":true,"revolt":true,"rifftrax":true,"rthtv1":true,"retrotv":true,"revnaction":true,"reuters":true,"rightnowtv":false,"redapple21not247":true,"rtvius":true,"runtime":true,"rtenespanol":true,"roar":true,"rockyhillgovernmentaccesschannel16":false,"radiomensajetv":true,"runtimeespanol":true,"revryher":false,"revrylatinx":true,"sanskarusa":false,"rvtvgrantspass":true,"rvtvcivic":true,"riflecommunitytvrctv":true,"ryanandfriends":true,"samsungwildlifegeoblocked":true,"salemnewschannel":true,"revry":true,"revryqueer":true,"scaresbyshudder":true,"sccurrents":true,"rvtvvoices":true,"rvtvprime":true,"rvtv":true,"santamariacommunitytelevisioneducationchannel":true,"plutotvaction":true,"secnetwork":true,"santamonicacitytv20not247":true,"schwabnetwork":true,"screendreams":true,"semillitastv":true,"santamariacommunitytelevisiongovernmentchannel":true,"paramountpicks":true,"santamariacommunitytelevisionpublicaccesschannel":true,"scientologynetworkkscndt1":false,"scientologynetwork":false,"senttvglobalnetworkatlanta":true,"scientologynetworkwfttdt1":false,"perrymason":true,"scrippsnews":true,"shoplc":true,"showtime":false,"sfgovtv2sanfranciscothecitychannel":true,"shouttv":true,"showtimefamilyzone":true,"sfgovtvsanfranciscothegovernmentchannel":true,"swat":false,"slocountychannel21":true,"smithsonianchannel":true,"sgtv":true,"snlvault":false,"sanctuary":true,"soreal":false,"sbntv":true,"sfcommonschannel76":true,"plutotvlives":true,"shalomtvnot247":true,"sfcommonschannel29":true,"shabakeh7":true,"shemaroobollywood":true,"sonycanalnovelas":false,"slopestv":true,"sportsmanchannel":true,"sportsnetnewyork":true,"skwad":true,"spikeoutdoors":true,"spikeplutotv":true,"sonictv":true,"startrekdeepspacenine":true,"startrek":true,"stadium":true,"rtrplanetausageoblocked":true,"startrekthenextgeneration":true,"spirittvnot247":true,"starttv":true,"sportsgrid":true,"scvtv":true,"showtimeextreme":true,"stpetetv":true,"plutotvfantastic":true,"sonykalhindi":true,"starzcinema":true,"starz":true,"starzkidsfamily":true,"starzcomedy":true,"stingraygreatestholidayhits":false,"sundancetv":true,"showtime2":true,"plutotvcrimemovies":true,"storytelevision":true,"supersimplesongs":true,"sumtvenglish":true,"sumtvlatino":true,"lifetimemovieswest":false,"talkinliveclassicstv":true,"stluciepublicschools":true,"lifetimewest":false,"plutotvicons":true,"plutotvstaffpicks":true,"storiesbyamc":true,"syfy":true,"stryktv":true,"sitcomlegends":true,"tbn":true,"swervecombat":true,"survivor":true,"tbninspire":true,"stocktongovtv":false,"teennick":true,"tastemadetravel":true,"ted":true,"tampabaycommunnitynetworktbcn":true,"teleboston":true,"tct":true,"speedvision":false,"tastemade":true,"telemundoaldia":false,"telemundotelenovelasclsicas":true,"telehitestadosunidos":true,"telehitmusicaestadosunidos":true,"telepam":true,"starinternational":true,"superchannelorlando":true,"telemundocorpuschristi":true,"telemundo":false,"theaddamsfamily":true,"startrekvoyager":true,"theamazingrace":true,"taiwanplustv":false,"theandygriffithshow":true,"telemix":true,"tennischannel2":true,"tapesh2":true,"theasylum":true,"tevevidanetworknot247":true,"swamijitvamericannot247":true,"thebobrosschannel":false,"thechallenge":true,"storagewarsbyae":true,"tbnarmenia":true,"thearchive":true,"thecowboychannel":true,"thecarolburnettshow":true,"terramaterwildenglish":true,"thehilltvgeoblocked":false,"theconnersgeoblocked":true,"supernaturaldrama":true,"soundviewcommunitymediaeducation":true,"thecountrynetwork":true,"thedesignnetwork":true,"thenewdetectives":true,"tempechannel11":true,"tennischannel":true,"thejohnnycarsonshow":true,"thefilmdetective":true,"thechatshowchannel":true,"thefirsttv":true,"thenest":true,"thenownetworknot247":true,"thejamieoliverchannel":true,"therifleman":true,"thetwilightzone":true,"thelegochannel":true,"thepetcollectivegeoblocked":true,"theyoungturksgeoblocked":true,"thewalkingdeaduniverse":true,"theohiochannel":false,"thewordnetwork":true,"temeculatv":true,"thewalktv":false,"thepriceisright":true,"thewalkingdeadenespaol":true,"thegrahamnortonshow":true,"thepriceisrightthebarkererageoblocked":true,"threescompany":true,"thisoldhouse":true,"tomandjerry":true,"tintv":true,"timelesstv":true,"tinyhousenation":true,"topstoriesbynewsy":true,"thedovetv":true,"tosh0":true,"todayallday":true,"totallyturtles":true,"torranceciticable":false,"toongogglesjunior":true,"toongoggles":true,"traverseareacommunitymediacommunitytvchannel189geoblocked":true,"tmzgeoblocked":true,"thegoodwife":true,"tlnmediasanfrancisco":true,"thorntongovernmentaccesschannel17":true,"tribecachannelgeoblocked":true,"truecrimenetworkgeoblocked":true,"turismohd":true,"tvland":true,"truehistory":true,"tutv":true,"tvone":true,"truecrimenow":true,"tstv":true,"toonamiaftermatheast":true,"tvlandsitcoms":true,"tbnpacific":true,"tlnmediachicago":true,"mgmmarquee":false,"thewildwildwest":true,"mgmwest":false,"tveinternacionalamericahdgeoblocked":true,"tveinternacionalamericageoblocked":true,"tvsciphernetwork":true,"tvsboxing":true,"tvsbowlingnetwork":true,"tvsclassicmovies":true,"tvdajanot247":true,"tvsclassicsports":true,"tvscomedynetwork":true,"tvquisqueya":true,"news12connecticutgeoblocked":false,"teenmom":true,"tv4":true,"tvhispanicnot247":true,"toughjobs":true,"tvsnostalgia":true,"tvsnostalgiamovies":true,"tvsdriveinmovie":true,"tvspetparadenetwork":true,"tvsmainstreetnot247":true,"tvsselectnetwork":true,"tvspinballnetwork":true,"tvsmusicnetwork":true,"tvshitops":true,"tvsquizshownetwork":true,"tvsfilmnoirnetwork":true,"tvsfamilychannel":true,"tvshollywoodhistory":true,"tvsflashbacknetwork":true,"tvsagovernmentchannel":true,"tvsapublicchannel":true,"tvssportsnot247":true,"tvssportsbureau":true,"tvsvintagenetwork":true,"tvstravelnetworknot247":true,"tvpanounot247":true,"tvswesternmovie":true,"tvswomensports":true,"tvsturbo":true,"tvsconsumerdirect":true,"tvstelevisionnetwork":true,"tvstavern":true,"unimascentral":true,"tvstallyho":true,"unidentified":true,"usanetworkwest":true,"uptv":true,"usanetwork":true,"uctvuniversityofcalifornianot247":true,"unbeaten":false,"univision":true,"unimasmountain":true,"tycsportsusa":false,"usatoday":true,"vbstvnot247":true,"unsolvedmysteries":true,"tvstalknetwork":true,"vallenatointernacionalnot247":false,"valleyshorecommunitytelevision":true,"venevisininternacional":true,"smithsonianchannelselects":true,"vevopop":true,"vevohiphop":true,"vevo90s":true,"vevolatino":true,"vevo80s":true,"vh1":true,"vevocountry":true,"vh1west":true,"vevorb":true,"vevo2k":true,"visionlatinanetwork":true,"villageofhastingsonhudsonny":true,"vevotrueschoolhiphop":true,"vicetv":true,"vevoretrorock":true,"w14dkd141tvdelmarva":true,"universalcomedy":true,"universalcrime":true,"vidamejortv":true,"w14dkd142newsnet":true,"vevo70s":true,"w14dkd145allsportstelevisionnetwork":false,"voatvafrica":true,"voapersian":true,"vsin":true,"vtnvictorytelevisionnetwork":true,"wbtscd1":false,"vegaslifetv":true,"watchitscream":true,"watchitkid":true,"wanteddeadoralive":true,"wcaudt1":false,"waypointtv":true,"watctv57":true,"univisionwest":false,"wcbstv21":true,"velayattv":true,"watctheloop":true,"watcthepointnetwork":true,"wdaftv42":true,"wetv":true,"weathernation":true,"wbrzweatherchannelbatonrougela":true,"weatherspy":true,"universalcinema":false,"wfutdt1geoblocked":true,"transformerstv":true,"westerntv":true,"wgaldt3geoblocked":true,"wedqdt4":true,"wcetvdigitalchannel318":true,"wbtvnews":true,"wbbj":true,"wcca194worcesterma":true,"wggsdt1":false,"wftxnewsfortmyersfl":true,"wgndt1":true,"wggsdt2":true,"whiplashcinema":true,"whiplash":true,"whiplashii":true,"whiteplainscommunitymedia":true,"westerns4u":true,"wcot13":true,"whbqdt1":true,"wdeftvnewschattanoogatn":true,"vh1queensofreality":true,"windowtv":true,"wflddt1":true,"wcbi":true,"wildnout":true,"wgtvdt3":true,"tvlanddrama":true,"willowsports":true,"wfxtdt2":true,"sketchyaf":true,"whpsdetroit":true,"wltvdt1geoblocked":true,"westhollywoodwehotv":true,"whiodt1":true,"wnbcdt1":false,"wipeoutxtra":true,"wired2fishgeoblocked":true,"wlmb":true,"wmptdt2":true,"witn22not247":false,"wjaxdt1":true,"whittiercitytv":true,"worldfishingnetwork":true,"womenssportsnetwork":true,"theloveboat":true,"witidt1":true,"weedsnursejackie":true,"wrcdt1":false,"worldpokertour":false,"winewatcheswhiskey":true,"wptvnewswestpalmbeachfl":true,"wolcottgovernmentaltv":false,"worldharvesttv":true,"wjbkdt1":true,"worldchannel":true,"wtvjdt1":true,"wpstv":true,"thejudgejudychannel":true,"wtnhdt1":true,"wsocnowgeoblocked":true,"wslfld351":true,"wutangcollection":false,"wnywdt1":true,"winthropcommunityaccesstvnot247":false,"wxtvdt1":true,"willow":true,"wvitdt1":false,"wvvhcd181":true,"wlngradionot247":true,"wsbsdt1":true,"wsocdt1":true,"wwontvch48":true,"wpxidt1":true,"wmgttvnews":true,"xitenuevolatino":false,"wvculpconcorduniversityradiothecure977":true,"xite90sthrowback":false,"youdotgov":true,"wsbdt1":true,"yahoofinance":true,"wttgdt1":true,"xitejustchill":true,"wjxtnews4jax":true,"xitesiemprelatino":false,"xiterockxmetal":true,"yomtv":true,"yesnetwork":true,"wtxfdt1":true,"xitereggaevibes":true,"nickelodeonwest":false,"wmbcdt1":false,"wipeout":true,"xiteclassiccountrygeoblocked":true,"zarintv":true,"xfctv":true,"ytatv":true,"yugioh":true,"younghollywoodgeoblocked":true,"wtvqabc36news":true,"yumaazch72":true,"yumaazch73":true,"wtvtdt1":true,"yugiohenespanol":true,"wxxvtvnews":true,"xplore":true,"wwordt1":false,"zoomtvkurdish":true,"international":true,"yuma77":true,"syfywest":false,"telemundowest":false,"tempoafrictv":false,"tudn":false,"unimas":false,"univisiontlnovelas":false,"unimaswestgeoblocked":false,"vallejocommunityaccesstelevision":false}}