{"generatedAt":"2026-07-17T07:34:41.839182+00:00","channels":{"24hourfreemovies":false,"ae":true,"aewest":true,"00sreplay":true,"3abndaretodreamnetwork":true,"3abnlatino":true,"3abnpraisehimmusicnetwork":true,"3abnproclaimnetwork":true,"3abnkidsnetwork":true,"70scinema":true,"3abnenglish":true,"3abnfrench":true,"aabctv":true,"abc":true,"90sthrowback":true,"abc5":true,"abc2baltimoremd":true,"abc5bostonma":true,"abc6indianapolisin":false,"abc7albuquerquenm":true,"abc6columbusoh":true,"abc2portlandor":true,"abc9manchesternh":true,"30ainvestmentpitch":true,"30atvclassicmovies":true,"30agolfkingdom":true,"30atelevisionchannel":true,"30awelovecars":true,"30aridiculoustv":true,"30aloomeredtv":true,"30asidewalks":true,"30aluxelifediscovered":true,"30alionelnationtv":true,"30athebeachshow":true,"30ageorgiahollywoodreviewtv":true,"30adarcizzleoffshore":true,"30amusic":true,"abc9tucsonaz":true,"abc4charlestonsc":true,"abc5stpaulmn":true,"abc9orlandofl":true,"abc6austintx":true,"90skids":true,"90skidstv2":true,"abc12milwaukeewi":true,"abc15phoenixaz":true,"50centaction":true,"abc10sandiegoca":true,"abcnewslive5":true,"abcnewslive1":true,"abcnewslive8":true,"abc7denverco":true,"abc23bakersfieldca":true,"abc4seattlewa":true,"abc7washingtondc":true,"abc13lasvegasnv":true,"abcnewslive6":true,"abc22daytonoh":true,"abcnewslive3":true,"abcnewslive9":true,"accnetwork":true,"abc25newscentraltexas":true,"abc13ashevillenc":true,"abnafrica":true,"abc10duluthmn":true,"abc27tallahasseefl":true,"abcnewslive4":true,"abnafghanistan":true,"abc15myrtlebeachfl":true,"abcnewslive10":true,"abcnewslive7":true,"48hours":true,"abnchina":true,"abntvindia":true,"abnbiblemovies":true,"abnurdu":true,"afvenespaolnot247":false,"accuweathernetwork":true,"accesssacramentochannel17":true,"80srewind":true,"accdn":true,"abcnewslive2":true,"access19":true,"afrolandtv":true,"accessmediaproductionschannel":true,"accessmediaproductionsmontereychannel":true,"akctvpuppies247":true,"accessmediaproductionscommunitychannel":true,"akctvmeetthebreeds":true,"abcwway3":true,"accessmediaproductionspeninsulachannel":true,"accessmediaproductionsmarinatv":true,"access4pac":true,"actv":true,"akaku53":true,"akaku54":true,"accuweathernow":true,"akaku55":true,"abcwest":true,"akctv":true,"alkarmatvaustralia":true,"acapulcoshore":true,"alhorreyatv":true,"accessnashua":true,"almahditv":true,"alfadytvnot247":true,"allblkgems":true,"accessvisionchannel17":true,"altitudesports":false,"alhurrairaq":true,"amc":true,"allrealitywetv":true,"alkarmatvmiddleeastnot247":true,"allweddingswetvgeoblocked":true,"accesstuolumne":true,"accessvisionchannel16":true,"alkarmatvfamilynot247":true,"alkarmatvpraisenot247":true,"alkarmatvtalmazanot247":true,"aftv":true,"acetv":true,"amgatvnot247":true,"adrenalinapuratv":true,"almagdtvmiddleeastnot247":true,"amcabsolutereality":true,"amcenespaolgeoblocked":true,"aghapykids":true,"alabamaweathernetwork":true,"artntvnot247":true,"amgtv":true,"alwaysfunnyvideos":true,"albdreamstv":true,"antennatv":false,"americasfunniesthomevideos":true,"americastestkitchengeoblocked":true,"arkansaspbsgeoblocked":true,"americasvoicenews":true,"assyriasatnot247":true,"ameritradenot247":true,"asiancrush":true,"accesshumboldt":true,"americasvoice":true,"aspire":true,"animationgeoblocked":true,"alientovisionnot247":true,"animexhidivegeoblocked":true,"abcmiamifl":true,"arydigitalusanot247":false,"atlantachannel":true,"athomewithfamilyhandyman":true,"antiquesroadshowuk":true,"angermanagementchannel":true,"amazingfactstv":true,"axstv":true,"amceast":true,"aweinternational":true,"antiquesroadshowpbs":true,"awe":true,"aweplus":true,"auroratv":true,"babyfirst":true,"alkarmatvyouthenglishnot247":true,"atxn2":true,"alkarmatvnorthamericacanadanot247":true,"arewethereyet":true,"americasnexttopmodel":true,"babytvus":true,"almagdtvnorthamerica":true,"bbcamerica":true,"atxn3":true,"atl26":true,"autentichistory":false,"babysharktv":true,"atlas":true,"artflixmovieclassics":true,"atxn1":true,"asianculturetv":true,"babytvlatinamerica":true,"bbcfood":true,"bbcamericaeasthd":true,"barktv":true,"bandamaxusa":true,"bbchomegarden":true,"americanhorrors":true,"autentictravel":false,"backstage":true,"beachtvpanamacity":true,"beachtvfloridaalabama":true,"beachtvmyrtlebeachthegrandstrand":true,"beinsportsusa":true,"beinsportsxtra":true,"bbcdoctorwhoclassic":true,"beinsportsxtraenespanol":true,"betcinema":true,"bet":true,"betgospel":true,"betherwest":true,"bether":true,"betjams":true,"betsoul":true,"avangtv":true,"betwest":true,"baywatch":true,"berkscommunitytv":true,"amutv":true,"beachtvkeywestfloridakeys":true,"beverlyhillstelevision10":true,"b4umoviesusa":false,"beverlyhillstelevision35":true,"bbckids":false,"betterlifenaturechannel":true,"betterhealthtv":true,"betterlifetv":true,"bigtennetwork":true,"betplutotv":true,"barrescue":true,"bektvnews":true,"bbcearth":true,"bektvsportswest":true,"bigcommunitychannel":true,"bigcivicchannel":true,"battlestargalactica":true,"biztv":true,"bloombergtv":true,"binge":true,"billiardtvgeoblocked":true,"bluestv":true,"betclassics":true,"bestofdrphil":true,"bloombergoriginals":true,"bounce":true,"blacknewschannel":true,"betthrowbacks":true,"betvisionaries":true,"boltoncommunityvoicechanneleducation":true,"boltoncommunityvoicechannelpublic":true,"boltoncommunityvoicechannelgovernment":true,"bravo":true,"beverlyhillbillies":true,"britboxmysteries":true,"beverlyhills90210":true,"bloomfieldaccesstvchannel5":true,"bloomfieldaccessgovernmenttv":true,"bmchdtv":true,"beyondthegates":true,"bravowest":true,"bouncexl":true,"buzzr":true,"bonapptit":true,"bloombergtvusliveevent":true,"bigbrother":true,"bxarts":true,"blazelive":true,"cspan":true,"cspan2":true,"byutv":true,"bxinspire":true,"bxinform":true,"bloombergtvuspoliticsliveevent":true,"bxculture":true,"bpxtvradio":true,"bluebloods":true,"bxomni":true,"butv10not247":true,"brevardcountygovernmentaccesstv":true,"burbankchannel":true,"buenaparktelevision":true,"catholictv":true,"catchycomedy":true,"bonanza":true,"canaldelafe":true,"businessrockstars":true,"camerasmile":true,"carlsbadcitytvchannel":true,"cbs2saltlakecityut":true,"canelatv":true,"cbnespanol":true,"cbnnewschannel":true,"campspoopy":true,"cbnfamily":true,"cbs3kalamazoomi":true,"calabasaschannel":true,"californiamusicchannel":true,"cbs4elpasotx":true,"cbs12westpalmbeachfl":true,"cantv21":true,"cantv27":true,"cantv36":false,"cbs8desmoinesia":true,"cantv19":true,"cbs22southbendin":true,"cbsenespaol":true,"cbs42austintx":true,"cbs21harrisburgpa":true,"cafetradetv":true,"cbsnewsbaltimore":true,"bellatormma":true,"cbssportsgolazonetwork":false,"cbsnewsdetroit":true,"cbsnewssacramento":true,"cbs3omahane":true,"cbsnewsnewyork":true,"cbsnewscolorado":true,"cbssportsnetworkusa":true,"cbssportshqgeoblocked":true,"cbs6richmondva":true,"cbsnewsbayarea":true,"cbsnewspittsburgh":true,"celebritynamegamegeoblocked":true,"cbsnewsphiladelphia":true,"cbsnewsboston":true,"cbsnewsminnesota":true,"cbsnewslosangeles":true,"ccx1":true,"cbsnewsmiami":true,"cbsnewschicago":true,"carchase":true,"cbs":true,"channel11":true,"channel18gac":true,"charge":true,"cheddaru":true,"celebrityscenetv":true,"cbs9oklahomacityoknot247":true,"chinohillscitytvchannel341":true,"cheddarnews":true,"cbs12cincinnatioh":true,"cbswest":true,"cineadrenalina":true,"chefrocshownot247":true,"chefchampionnot247":true,"cinepremiere":true,"brattv":true,"betcomedymovies":true,"cinevault80s":false,"christianyouthchannel":true,"cfmtvchannel98":true,"cerritostv3":true,"cinevaultwesterns":false,"blackinkcrew":true,"cinemexicano":true,"channel10":true,"charlottecountycctv":true,"cineromantico":false,"cinesony":true,"citytvsandiego":true,"cfncatholicfaithnetwork":true,"cinepride":true,"cityofmonroegovernmentchannel":true,"channelone":true,"circle":true,"clarity4kgeoblocked":true,"choppertown":true,"cmt":true,"cleotv":true,"classica":true,"classiccinemanot247":true,"cloudflaretv":true,"cnbc":true,"cmtequalplay":true,"cityofoakland":true,"cheersfrasier":true,"classictvdrama":true,"comedycentral":true,"comedycentralanimation":true,"coldcasefiles":true,"comedytv":true,"cineamor":true,"cineenespaol":true,"comet":true,"comedydynamics":false,"coasttvnbcnot247":false,"cmcusacountrymusicchannel":true,"cbsnews247":true,"champaigngovernmenttelevision":true,"cinecomedia":true,"courttv":true,"cozitv":true,"cookingpanda":true,"classicmoviewesterns":true,"cornerstonetv":true,"classicmovieschannel":true,"classictvcrimedrama":true,"classictvfamilies":true,"create":true,"crimeinvestigation":true,"concordtv":true,"comerciotv":true,"colliertelevisionctv":false,"cruztv":true,"creatvbayvoicetvchannel27":true,"csattvnot247":true,"citytvcapitalcityconnectionnot247":true,"cops":true,"costamesasmunicipalaccesschannelcmtv3":true,"contracostacollegetvgeoblocked":true,"comedycentralenespaol":true,"comedycentralplutotv":true,"curiositynow":true,"creatvclassroomschannel28":true,"cineterror":true,"creatvcommunitychannel15":true,"creatvtheoutletchannel30":true,"crime360":true,"concertchannel":true,"dabl":true,"cw":true,"cineaventura":true,"ctn":true,"ctnlivestream2not247":true,"ctntvconneticutnot247":true,"ctncourtfeednot247":true,"dateline247":false,"cvtvchannel192":true,"cypresspublicaccesschannel36":true,"dccouncilchannel":true,"blackfamilysitcoms":true,"delmartv":false,"crunchyroll":true,"daystartvespanol":false,"dangertv":true,"darkmattertv":true,"csi":true,"csimiami":true,"csienespaol":true,"denver8tv":true,"depeliculaus":true,"cupertinocitychannel":false,"coralgablestelevision":false,"csiny":true,"degrassi":true,"dealornodeal":true,"dcgovcouncilhearingroom120":true,"dcgovdkn":true,"cvtvchannel194":true,"disneychannel":true,"divaadria":false,"disneyjuniorwest":true,"disneychannelhdeast":true,"derrytv17":true,"daystartv":true,"disneyjunior":true,"disneyxd":true,"detroitchannel10":true,"degatvnot247":false,"detroitchannel68":true,"donttellthebride":true,"detroitchannel22":true,"detroitchannel21":true,"dogthebountyhunter":true,"documentary":false,"datingdisasters":true,"dogtv":true,"drgenescott":true,"dovechannel":true,"ebonytvbylionsgate":true,"designatedsurvivorgeoblocked":true,"e":true,"ewest":true,"drphilsmerittv":true,"duckhuntingtv":true,"derrytv23":true,"drybarcomedy":true,"dccmakingtheteam":true,"draftkingsnetwork":true,"elsembradornuevaevangelizacionesne":true,"dogelcazarrecompensas":true,"dungeontv":true,"ebscinema":true,"elbesharagtvnot247":true,"ebsmusika":true,"districtofcolumbianetwork":true,"csimiamienespaol":true,"espnews":true,"espndeportes":true,"etvteluguusa":true,"entertainmenttonight":true,"espnu":true,"estrellagames":true,"csinyenespaol":true,"elrey":false,"didgahtv":true,"entrepreneurtv":true,"elreinoinfantil":true,"fanduelracing":false,"ekeepingup":true,"electricnowgeoblocked":true,"fandueltv":true,"fernandinabeachcitymeetingnot247":true,"extrematv":true,"disneyxdwest":true,"fetv":true,"escambiacountytvectv":true,"f1channelgeoblocked":true,"estrellanews":true,"costv":true,"fashionfinds":true,"classictvcomedy":true,"ewtngeoblocked":true,"ewtnspanishgeoblocked":true,"fite247":false,"fifaunitedstates":false,"filmrisewesterns":true,"docurama":false,"failarmyinternational":true,"dynasty":true,"estrellatv":true,"crmenesimperfectos":true,"flix":true,"fgtv":true,"filmriseanime":true,"fairfieldgovernmentaccesschannel26geoblocked":true,"fox13seattlewa":true,"foreverkids":true,"fox2sanfranciscoca":true,"fideletv":false,"fox":true,"fortpiercelivestream":true,"fox45baltimoremd":true,"filmriseclassictv":false,"fearfactor":true,"foxdeportes":false,"fox11greenbaywi":true,"fnxgeoblocked":true,"fox26visaliaca":true,"foxsoul":false,"fox25oklahomacityok":true,"fnx":true,"forensicfilesgeoblocked":true,"foxbusinessnetwork":true,"foxnewschannel":true,"filamtvnetwork":true,"foxsoccerplus":true,"fox23capegirardeaumonot247":true,"freeformwest":true,"familyties":true,"fubosportsnetwork":true,"farscape":true,"freeform":true,"fcpublicmedia":true,"fortcollinscabletv":true,"feelgooddrama":true,"freebietvnot247":false,"fresnocmac2educationchannel":true,"fresnocmac1publicchannel":true,"foxnewsradio":true,"fuse":true,"fx":true,"fresnocmac3governmentchannel":true,"fontanacommunitytelevisiongeoblocked":true,"flowerstvusa":false,"fxm":true,"fyi":true,"estrellasdeaccin":true,"foxweathergeoblocked":true,"fxx":true,"ftfsports":true,"foxwest":true,"freespeechtv":true,"fyiwest":true,"galavision":true,"galavisionwestgeoblocked":true,"foxsports1":true,"gameshownetwork":true,"frightflix":true,"forensicfiles":true,"flicksoffury":true,"gilroycmaptvchannel18":true,"funroads":true,"gebtv":true,"glendale11az":true,"galxytv":true,"globalfashionchannel":true,"gilroycmaptvchannel17":true,"gainesvillecommunity12tv":true,"godslearningchannel":true,"gilroycmaptvchannel20":true,"gillettepublicaccesstelevisionchannel192":true,"gillettepublicaccesstelevisionchannel190":true,"gameshowcentral":true,"golazonetwork":true,"golfchannel":false,"gillettepublicaccesstelevisionchannel189":true,"goodlife45not247":true,"ganjehozourtv":true,"gemshoppingnetwork":true,"gospeltruthtv":true,"gotravelergeoblocked":true,"funnyaf":true,"gravitasmovies":true,"greatamericanfaithliving":true,"greatamericanfamily":true,"greatentertainmenttelevision":true,"gousatv":true,"grit":true,"guangdongtvamerica":true,"gordonramsay":true,"harpalgeo":false,"globalworldtv":true,"gospelbroadcastingnetwork":true,"gritxtra":true,"grjngowesternmovies":true,"gagsnetwork":true,"hallmarkchannel":true,"glendaletvgeoblocked":true,"hallmarkmoviesmore":false,"happykids":true,"hallmarkfamily":true,"goldencommunitytelevision":true,"highvisionnot247":true,"hallmarkmystery":true,"gbnglobalbuddhistnetwork":true,"go2travel":false,"haddamkillingworthhighschooltvgeoblocked":true,"historyhit":true,"greensborotv":true,"hasbrolegendsgeoblocked":true,"gunsmoke":true,"heartland":true,"historywest":true,"hctvgovernmentchannel":true,"garfieldandfriends":true,"history":true,"hmongstartvnot247":true,"hctveducationalaccesschannel":true,"hmongtvnetwork":true,"hisglorytv":true,"hctvpublicaccesschannel":true,"fox25bostongeoblocked":true,"hiyah":true,"girlfriends":true,"hollywire":true,"hsnwest":true,"homeful":true,"hsn2":true,"hmipromznews":true,"hsn":true,"humormill":false,"ilovelucy":true,"htv1houstontelevision":true,"hillsboroughcountytvhtv":true,"htv2houstontelevision":true,"foxsports2":true,"haunttv":true,"globalchristiannetworkamerica":true,"ifc":true,"inthekitchen":true,"happydays":true,"impactnetwork":true,"gmtv":true,"gunaztv":false,"hope4lifetv":false,"hungry":true,"impossiblequizshow":true,"insp":true,"infowarsnetwork":true,"infast":true,"i24newsenglishusa":false,"itiswrittentv":true,"hogansheroes":true,"ionplus":true,"gilroycmaptvchannel19":true,"hopechannelnorthamerica":true,"hopechannelinternational":true,"itssupernaturalnetwork":false,"jewishlifetelevision":true,"harvestusa":true,"huntingtonbeachtvchannel3":true,"homemadenation":true,"hotbench":true,"jacksonvilleonslowgovernmenttelevision":true,"judgenosey":true,"hopechannelinteramericaenglish":true,"hopechannelinteramerica":true,"inwild":true,"icarlytv":true,"jbs":true,"kadntv151":true,"justicecentraltv":true,"journytv":true,"iongeoblocked":true,"kcatpublicmediatv":true,"kbevspectrumchannel6beverlyhills":false,"inkmaster":true,"kcontentbycjenm":true,"instantsaga":true,"kerncountytelevision":true,"kaloopytv":true,"iranefardatv":false,"kcmnld6":true,"investiga":true,"jewelrytelevision":true,"jewelrytv2":true,"ironchef":true,"kcksld253":true,"kajoutvnot247":true,"kdfwdt1":true,"klfytv101":true,"ketchuptv":true,"kftrdt1geoblocked":true,"kmexdt1geoblocked":true,"jerseyshore":true,"katc31":true,"justforlaughsgags":true,"kdvr311":true,"kpvmacecountryradio":true,"kmctdt1":false,"kntvdt1":false,"kbribrightonchannel8":false,"kpvmprimetv25":true,"kpvmoanplus":true,"kmspdt1":true,"kpvmmovies":true,"kpvmnewsmax2":true,"kpvmaweplus":true,"kpvmrealamericasvoice":true,"kirodt1":true,"kidsflixnot247":true,"kpvmstorytelevision":true,"kartoonchannel":true,"kuvndt1":true,"kqeddt2":true,"krgvdt2geoblocked":true,"lacrossetv":true,"kitv4islandnews":true,"kvvbtv33victorvalleynot247":true,"kviedt2":true,"kscevidacristiana":true,"ktbcdt1":true,"krcatvestrellalosangeles":true,"kokidt1":true,"ksazdt1":true,"laff":true,"krivdt1":true,"kxasdt1":false,"krisdt1":true,"kttvdt1":true,"lawndalecitytv":false,"lavozdejesushd":true,"ktoo360tv3":false,"kshb41":true,"kqslchannel8":true,"lawcrime":true,"kidsmovieclub":true,"latvgeoblocked":true,"kztvdt1":true,"legokidstv":true,"lifechristianbroadcastingnetwork":true,"lifeendtimestv":true,"leominstertveducational":true,"lifetime":true,"lifetimemovies":true,"lifetimerealwomen":true,"lifetimemovieswest":true,"lifetimewest":true,"lacityview35":false,"lakewoodcitytv":true,"lbcinternational":true,"lasvegastonightwithdaledavidson":true,"lightinglivesblessingnationshisword":true,"leominstertvpublicnot247":true,"latinochanneltv":true,"lgtv":true,"lindelltv":true,"laquebuenaatlanta":true,"lightinglivesblessingnationstvchinese":true,"lightinglivesblessingnationstvkorean":true,"lightinglivesblessingnationshislight":true,"lifevisiontvnot247":true,"lextv":true,"leominstertvgovernment":true,"littlestarsuniverse":true,"lhcaztv":true,"lightinglivesblessingnationstvarabic":true,"lakewoodchannel8":false,"lightinglivesblessingnationstvlatino":true,"lightinglivesblessingnationssmartlifestyletv":true,"lolnetwork":false,"livingfaithtv":false,"localish":true,"logostvnot247":false,"leesburglakefronttv":true,"lonestar":true,"lightinglivesblessingnationstvromanian":true,"losangeleslocaltelevisionchannel36":true,"longbeachtelevision":true,"littleguyanatv":true,"lightinglivesblessingnationstvsouthasia":true,"lompoctaptvchannel23":true,"lompoctaptvchannel24":true,"lompoctaptvchannel25":true,"lovelandtv":true,"lovehiphop":true,"livenowfromfoxgeoblocked":true,"lptv":true,"littleton8tv":false,"lovetheplanet":true,"indimusictv":false,"luckydog":true,"magellantvnow":true,"magnificentmoviesnetwork":true,"livexlive":true,"madeinhollywood":true,"lovenatureenespanolgeoblocked":true,"lovepets":true,"maddogandmerrillnot247":true,"marqueesportsnetwork":true,"matlock":true,"livemusic":true,"mediasetitaliausa":true,"majestadtelevisinnot247":true,"maverickblackcinema":true,"mbcamerica":true,"manateeschoolstelevisionmstv":true,"losnuevosdetectives":true,"loveworldusa":true,"metv":true,"mcn6not247":true,"logostvenglishnot247":true,"mcn6artschannelnot247":true,"mcn6musicchannelnot247":true,"metvtoons":true,"luchalibreaaa":false,"martincountymctv":true,"mgm":true,"mgmdrivein":true,"midnightpulp":true,"miamibeachtv":true,"mgmhits":true,"mgmmarquee":true,"mbcmasrusa":true,"mbc1usageoblocked":true,"midpenmediacenterartsissuesandlifestyleschannel30":true,"midpenmediacenterdiversityandculturechannel75":true,"midpenmediacentergovernmentetcchannel26":true,"midsomermurders":true,"midpenmediacenteryoutheducationandsportschannel28":true,"midpenmediacentergovernmentetcchannel29":true,"mbcdramausa":true,"mbc3usageoblocked":true,"msadrenalina":true,"mlbnetwork":true,"missiontvnot247":true,"mlbchannelgeoblocked":true,"millbraecommunitytelevision":false,"mlbstrikezone":true,"metaleitortv":true,"monroecommunitymediaeducationchannel":true,"mohabattv":true,"movies":false,"monroecountytelevisionmctv":true,"montgomerychannel":true,"monroecommunitymediapublicaccesschannel":true,"mobilecountypublicschoolstvnetwork":true,"moviesphere":true,"mmatv":true,"msnow":true,"msg":true,"moorparkgovernmentchannel":false,"mst3k":true,"ministeriolavozdeunremanentetv":true,"misteriosmedicos":true,"misteriossinresolver":true,"missionimpossible":true,"msg2":true,"msgplus":true,"minutoparaganar":true,"mtv":true,"logostvestudionot247":false,"logostvkidsnot247":true,"mtv2":true,"mrbeananimated":true,"logostvsaludnot247":false,"mrvtvchannel45":true,"mtvclassic":true,"mtvlive":true,"mrvtvchannel44":true,"mytvsanantoniotxnot247":true,"mtvu":true,"nashbridgeschannelgeoblocked":true,"moretvdrama":true,"mytimemovienetwork":true,"nationalgeographichdeast":true,"nattv":true,"mysterysciencetheater3000":true,"nationalgeographicwildhdeast":true,"nashuagtvchannel16nashuanh":true,"natickeducationchannel":true,"nationalgeographic":true,"nationalgeographicwest":true,"naruto":true,"nashuaetvchannel22nashuanh":true,"nationalgeographicwild":true,"nbc3lasvegasnv":true,"nbc3sacramentoca":true,"natickgovernmentchannel":true,"natickpublicaccesschannel":true,"nbc4sanantoniotx":true,"nbc8salinasca":true,"nbc6johnstownpa":true,"mtctv":true,"nbc4milwaukeewi":true,"nbc8lancasterpa":true,"nbc5chicagolivenews":false,"nbc9steubenvilleoh":true,"nbc":true,"nbc11baltimoremd":true,"mtvbiggestpop":true,"nbc10rochesterny":true,"nbc26greenbaywi":true,"motortrendfasttv":true,"nbc6santabarbaraca":true,"nbatvgeoblocked":true,"mtvenespaol":true,"nbc12winstonsalemnc":true,"nbc8limaohnot247":false,"mtvflowlatino":true,"nbc4albuquerquenm":true,"nbcnewsnowhd":true,"nbcsportschicago":true,"nbcsportsnow":false,"logoplutotv":true,"mtvspankinnew":true,"nbcuniversowest":true,"nbcsn":true,"nbcnewsnow":false,"nbcwestnot247":true,"nesn":false,"newportbeachtelevision":false,"nbccomedyvault":true,"nbclxhome":true,"newcanaantelevision79":true,"ncmgovernmentpolitics":true,"ncmmainchannel":true,"nbcwest":true,"nbcuniverso":true,"news12newyork":true,"nbc13albanyny":true,"ncmeducationalkidschannel":true,"nbclx":true,"news12longislandgeoblocked":true,"news12newjerseygeoblocked":true,"news12hudsonvalleygeoblocked":false,"newsmaxtv":true,"newsmax2":true,"newsnetnot247":true,"newsnation":true,"news12connecticutgeoblocked":true,"newsmaxspanish":true,"news12bronxgeoblocked":true,"nbc10providencema":true,"nickelodeonwest":true,"nflnetwork":true,"nickjr":true,"nhratv":true,"nickelodeonplutotv":true,"nickelodeon":true,"newsy":true,"ninjakidz":true,"nostthenostalgianetwork":false,"nicktoons":true,"notvneworleanstv":true,"mtvplutotv":true,"nflchannelgeoblocked":true,"nyxt":true,"nhlnetwork":true,"ntdtv":true,"nicktoonswest":true,"novelisima":false,"nrbtv":true,"ntdtvwest":true,"ntdtvenglish":true,"northmiamibeachtv":true,"olelocommunitymediachannel49":true,"olelocommunitymediachannel54":true,"olelocommunitymediachannel55":true,"moretvsitcoms":true,"olelocommunitymediachannel53":true,"onceninasyninos":false,"nickelodeonenespaol":true,"oanplus":true,"ontariopublicaccesschannel":true,"nickjrplutotv":true,"oneamericanewsnetwork":false,"moretruecrime":true,"outside":false,"oceansidecommunitytelevisioneducationandgovernmentchannel19":true,"norcastweather":true,"oceansidecommunitytelevisioncommunitychannel18":true,"outdoorchannelhd":true,"orangegovernmentaccesstv":true,"ovation":true,"overcomerstv":true,"pac12insider":true,"oxygen":true,"outersphere":true,"outdoorchannel":true,"outdooramerica":true,"omideiran":true,"pacificcoasttvhmbcoastsidechannel27":true,"overtime":true,"paramountmoviechannel":true,"paramountpicks":true,"paramountnetwork":true,"pacificcoasttvmwsdchannel26":true,"ontv4ugeoblocked":true,"palmbeachestv":true,"pasiones":true,"pbshonoluluhinot247":true,"pacificislandnetwork":true,"pbrridepass":true,"onepiece":true,"palmbeachcountytvchannel20":true,"pbctapeshtv":true,"pbsantiquesroadtrip":true,"payameafghantvnot247":true,"mgmwest":true,"pascotv":false,"pbsket2":true,"payvandtv":true,"payamearameshtv":true,"pbsketky":true,"pbsketworld":true,"pbskids":true,"pbsketlouisvilleky":true,"pbskids247":false,"pbslincolnnegeoblocked":true,"pbskidseasterncentral":true,"pbsretrogeoblocked":false,"parstv":true,"pbsmptbaltimoremd":true,"pbsnewjerseynjnot247":true,"pbskidspacific":true,"pbskidshawaii":true,"pbskidsalaska":true,"payamjavantvnot247":true,"pbskidsmountain":true,"peopleareawesome":true,"pbsnationaleastgeoblocked":true,"phxtv":true,"pbstravel":true,"newkmovies":true,"phillycam":true,"pbsnature":true,"pgatour":true,"pbssedaliabritishcolumbiamogeoblocked":true,"pixltv":true,"plutotvanimemovies":true,"phlgovtv":true,"plutotvcompetition":true,"newkpop":true,"plutotvcultfilms":true,"pinolecommunitytelevisionchannel26":true,"placidnot247":true,"pinolecommunitytelevisionchannel28":true,"peppapig":true,"plutotvhorror":true,"perrymason":true,"plutotvcrimedrama":true,"plutotvgameshows":true,"plutotvaction":true,"plutotvanime":true,"plutotvbackcountry":true,"plutotvcrimemovies":true,"plutotvromance":true,"plutotvfantastic":true,"plutotvdrama":true,"plutotvfranchisefavorites":true,"plutotvstaffpicks":true,"plutotvicons":true,"plutotvhometowndrama":true,"plutotvthrillers":true,"plutotvhistory":true,"plutotvmilitary":true,"plutotvlives":true,"plutotvwesterns":true,"pocketwatchgameon":true,"plutotvparanormal":true,"pokergo":false,"popstartv":false,"plutotvpride":true,"plutotvreaction":true,"plutotvscifi":true,"poptv":true,"pokmon":true,"positivtv":true,"plutotvcars":true,"portlandia":true,"poconotelevisionnetwork":true,"ptltelevisionnetwork":false,"plutotvterror":true,"pursuitchannel":true,"plutotvscience":true,"plutotvtrendingnow":true,"qvc3":true,"pompanobeachwebstreaming":true,"qvc":true,"qvc2":true,"raiworldpremium":true,"pursuitup":true,"portstluciepsltv":true,"plutotvtruecrime":true,"poudreschooldistricttv":true,"powernation":true,"rainbowruby":true,"pomonainternetstreamingchannel":true,"plutotvnovelas":true,"ranchocucamongarctv3":true,"pottadivinetvusa":true,"reelzfamousinfamous":false,"redseatthefirst":true,"rallytv":true,"radiotlkajounot247":false,"realwild":true,"radiotelesentinel":true,"radiotelepuissance":true,"radiotlwisdomnot247":false,"retrocrush":true,"revrynewsnot247":false,"redbulltvus":false,"revandroll":true,"realamericasvoice":false,"reuters":true,"plutotvadventure":true,"revolt":true,"galvestoncountytvnot247":false,"rfdtv":true,"radioytelevisinmart":true,"rifftrax":true,"rightnowtv":false,"revnaction":false,"retrotv":false,"riflecommunitytvrctv":true,"rawhide":true,"roar":true,"runtimeespanol":true,"revryher":false,"rthtv1":true,"rtenespanol":true,"revryqueer":true,"revry":true,"revrylatinx":true,"redapple21not247":true,"ryanandfriends":true,"sanskarusa":false,"rvtvcivic":true,"salemnewschannel":true,"rvtvgeoblocked":true,"rockyhillgovernmentaccesschannel16":false,"swat":false,"santamariacommunitytelevisioneducationchannel":true,"rtvius":true,"santamariacommunitytelevisiongovernmentchannel":true,"radiomensajetv":true,"santamariacommunitytelevisionpublicaccesschannel":true,"sccurrents":true,"samsungwildlifegeoblocked":true,"ridiculousness":true,"santamonicacitytv20not247":true,"scaresbyshudder":true,"scrippsnews":true,"scientologynetworkkscndt1":false,"scvtv":true,"scientologynetworkwfttdt1":false,"plutotvcomedy":true,"scientologynetwork":false,"secnetwork":true,"sfcommonschannel76":true,"sfcommonschannel29":true,"semillitastv":true,"runtime":true,"sfgovtv2sanfranciscothecitychannel":true,"screendreams":true,"sfgovtvsanfranciscothegovernmentchannel":true,"senttvglobalnetworkatlanta":true,"schwabnetwork":true,"shoplc":true,"shouttv":true,"showtime":false,"shemaroobollywood":true,"showtimefamilyzone":true,"rvtvprime":true,"rvtvvoices":true,"rvtvgrantspass":true,"sgtv":true,"soreal":false,"snlvault":false,"imantv":false,"skwad":true,"smithsonianchannel":true,"smithsonianchannelselects":true,"sanctuary":true,"sonykalhindi":true,"ocntv":true,"sonycanalnovelas":false,"soundviewcommunitymediaeducation":true,"shalomtvnot247":true,"slocountychannel21":true,"sportsmanchannel":true,"slopestv":true,"sonictv":true,"nosey":true,"sportsnetnewyork":true,"shabakeh7":true,"stpetetv":true,"jushindi":false,"jusone":false,"sbntv":true,"stluciepublicschools":true,"spirittvnot247":true,"juspunjabi":false,"spikeoutdoors":true,"starttv":true,"starz":true,"starzcomedy":true,"starzcinema":true,"sketchyaf":true,"starzkidsfamily":true,"stadium":true,"storytelevision":true,"sportsgrid":true,"sundancetv":true,"sumtvlatino":true,"sumtvenglish":true,"startrekdeepspacenine":true,"storiesbyamc":true,"stingraygreatestholidayhits":false,"startrekthenextgeneration":true,"survivor":true,"swervecombat":true,"syfywest":true,"rtrplanetausageoblocked":true,"speedvision":false,"spikeplutotv":true,"talkinliveclassicstv":true,"tbn":true,"supersimplesongs":true,"tbninspire":true,"stryktv":true,"tastemadetravel":true,"syfy":true,"ted":true,"startrek":true,"tbnarmenia":true,"taiwanplustv":false,"tampabaycommunnitynetworktbcn":true,"starinternational":true,"teennick":true,"telepam":true,"superchannelorlando":true,"telemundowest":true,"stocktongovtv":false,"tastemade":true,"telehitestadosunidos":true,"telehitmusicaestadosunidos":true,"telemix":true,"plutotvspotlight":true,"teleboston":true,"tapesh2":true,"telemundoaldia":false,"tempoafrictv":true,"tct":true,"telemundocorpuschristi":true,"thebobrosschannel":false,"thearchive":true,"supernaturaldrama":true,"theconnersgeoblocked":true,"temeculatv":true,"theasylum":true,"swamijitvamericannot247":true,"teenmom":true,"tennischannel":true,"thefirsttv":true,"tempechannel11":true,"thecowboychannel":true,"tevevidanetworknot247":true,"thehilltvgeoblocked":false,"terramaterwildenglish":true,"thedesignnetwork":true,"thejohnnycarsonshow":true,"storagewarsbyae":true,"thecarolburnettshow":true,"thecountrynetwork":true,"thechatshowchannel":true,"thejamieoliverchannel":true,"theaddamsfamily":true,"tennischannel2":true,"theamazingrace":true,"thefilmdetective":true,"theandygriffithshow":true,"thepriceisrightthebarkererageoblocked":true,"thetwilightzone":true,"thewalktv":false,"thenest":true,"thenownetworknot247":true,"thelegochannel":true,"tbnpacific":true,"theyoungturksgeoblocked":true,"thechallenge":true,"theohiochannel":false,"thegrahamnortonshow":true,"thepriceisright":true,"thepetcollectivegeoblocked":true,"thegoodwife":true,"thisoldhouse":true,"news12newyorkgeoblocked":false,"threescompany":true,"thewordnetwork":true,"thejudgejudychannel":true,"timelesstv":true,"thorntongovernmentaccesschannel17":true,"theloveboat":true,"thedovetv":true,"thewalkingdeaduniverse":true,"toongogglesjunior":true,"todayallday":true,"torranceciticable":false,"tintv":true,"tomandjerry":false,"tlnmediachicago":true,"thenewdetectives":true,"toongoggles":true,"telemundotelenovelasclsicas":true,"tudn":true,"toonamiaftermatheast":true,"truecrimenow":true,"tlnmediasanfrancisco":true,"sitcomlegends":true,"tstv":true,"topstoriesbynewsy":true,"tmzgeoblocked":true,"therifleman":true,"thewildwildwest":true,"tribecachannelgeoblocked":true,"thewalkingdeadenespaol":true,"tvhispanicnot247":true,"tvland":true,"turismohd":true,"tvdajanot247":true,"tutv":true,"traverseareacommunitymediacommunitytvchannel189geoblocked":true,"news12brooklyngeoblocked":false,"tvlanddrama":true,"news12conneticutgeoblocked":false,"tvone":true,"truecrimenetworkgeoblocked":true,"news12westchestergeoblocked":false,"tinyhousenation":true,"truehistory":true,"tvsbowlingnetwork":true,"totallyturtles":true,"startrekvoyager":true,"tvsciphernetwork":true,"tvsclassicmovies":true,"tvsboxing":true,"tv4":true,"tvsclassicsports":true,"tvscomedynetwork":true,"tvsdriveinmovie":true,"tvsfamilychannel":true,"tvsflashbacknetwork":true,"tosh0":true,"tvsfilmnoirnetwork":true,"tvshitops":true,"tvshollywoodhistory":true,"tvsmainstreetnot247":true,"toughjobs":true,"transformerstv":true,"tvsmusicnetwork":true,"tvpanounot247":true,"tvsnostalgia":true,"tvquisqueya":true,"tvsnostalgiamovies":true,"tvspetparadenetwork":true,"tvsagovernmentchannel":true,"tvsapublicchannel":true,"tvssportsnot247":true,"tvsquizshownetwork":true,"tvsselectnetwork":true,"telemundo":true,"tvssportsbureau":true,"tvspinballnetwork":true,"tvstalknetwork":true,"unimaswestgeoblocked":true,"tvstallyho":true,"unidentified":true,"unimascentral":true,"unimas":true,"tvsvintagenetwork":true,"tvstavern":true,"tvstelevisionnetwork":true,"tvsturbo":true,"tveinternacionalamericahdgeoblocked":true,"tvstravelnetworknot247":true,"uctvuniversityofcalifornianot247":true,"tvsconsumerdirect":true,"unsolvedmysteries":true,"tvlandsitcoms":true,"unimasmountain":true,"unbeaten":false,"uptv":true,"vevo2k":true,"usanetwork":true,"usanetworkwest":true,"vevo80s":true,"vevolatino":true,"vevocountry":true,"univision":true,"vevo70s":true,"tveinternacionalamericageoblocked":true,"vevohiphop":true,"tycsportsusa":true,"universalcomedy":true,"vevoretrorock":true,"venevisininternacional":true,"universalcrime":true,"vevo90s":true,"vevopop":true,"vh1":true,"vbstvnot247":true,"vevorb":true,"tvswomensports":true,"tvswesternmovie":true,"vicetv":true,"vh1west":true,"villageofhastingsonhudsonny":true,"visionlatinanetwork":true,"wanteddeadoralive":true,"usatoday":true,"w14dkd141tvdelmarva":true,"w14dkd145allsportstelevisionnetwork":false,"w14dkd142newsnet":true,"vtnvictorytelevisionnetwork":true,"vidamejortv":true,"voapersian":true,"waypointtv":true,"voatvafrica":true,"vegaslifetv":true,"valleyshorecommunitytelevision":true,"wbtscd1":false,"wcbstv21":true,"watctheloop":true,"universalcinema":false,"wbtvnews":true,"wcaudt1":false,"wcetvdigitalchannel318":true,"watcthepointnetwork":true,"watchitscream":true,"watchitkid":true,"watctv57":true,"wbrzweatherchannelbatonrougela":true,"wdaftv42":true,"wetv":true,"weathernation":true,"wfutdt1geoblocked":true,"velayattv":false,"weatherspy":true,"wedqdt4":true,"wggsdt1":false,"wgndt1":true,"wgaldt3geoblocked":true,"univisionwest":false,"wgtvdt3":true,"whiplash":true,"wflddt1":true,"wfxtdt2":true,"whiplashcinema":true,"whiteplainscommunitymedia":true,"whiplashii":true,"wftxnewsfortmyersfl":true,"wcot13":true,"vsin":true,"vevotrueschoolhiphop":true,"westerns4u":true,"vh1queensofreality":true,"wggsdt2":true,"whbqdt1":true,"wcca194worcesterma":true,"windowtv":true,"whpsdetroit":true,"willowsports":true,"westhollywoodwehotv":true,"weedsnursejackie":true,"whiodt1":true,"wdeftvnewschattanoogatn":true,"wltvdt1geoblocked":true,"wired2fishgeoblocked":true,"wmptdt2":true,"wcbi":true,"witidt1":true,"worldpokertour":false,"wlmb":true,"winewatcheswhiskey":true,"wjaxdt1":true,"wnbcdt1":false,"womenssportsnetwork":true,"worldfishingnetwork":true,"vallenatointernacionalnot247":false,"witn22not247":false,"worldchannel":true,"wrcdt1":false,"whittiercitytv":true,"westerntv":true,"wpstv":true,"wjbkdt1":true,"wipeoutxtra":true,"wlngradionot247":true,"wtnhdt1":true,"wutangcollection":false,"wvitdt1":false,"wsbsdt1":true,"wsocnowgeoblocked":true,"wptvnewswestpalmbeachfl":true,"wildnout":true,"wolcottgovernmentaltv":false,"wsbdt1":true,"wxtvdt1":true,"wvvhcd181":true,"wbbj":true,"wttgdt1":true,"wpxidt1":true,"winthropcommunityaccesstvnot247":false,"wtvjdt1":true,"worldharvesttv":true,"wtvtdt1":true,"wslfld351":true,"wmgttvnews":true,"wtxfdt1":true,"wsocdt1":true,"wipeout":true,"youdotgov":true,"yahoofinance":true,"yesnetwork":true,"xitejustchill":true,"xitereggaevibes":true,"wwontvch48":true,"xiteclassiccountrygeoblocked":true,"xiterockxmetal":true,"xfctv":true,"younghollywoodgeoblocked":true,"xite90sthrowback":false,"ytatv":true,"xitesiemprelatino":false,"yumaazch72":true,"wvculpconcorduniversityradiothecure977":true,"xitenuevolatino":false,"yumaazch73":true,"xplore":true,"wtvqabc36news":true,"yugioh":true,"wmbcdt1":false,"wjxtnews4jax":true,"zarintv":true,"yomtv":true,"wxxvtvnews":true,"yugiohenespanol":true,"yuma77":true,"wwordt1":false,"zoomtvkurdish":true,"international":true,"wnywdt1":true,"univisiontlnovelas":false,"vallejocommunityaccesstelevision":false}}